[
  {
    "uid": "APT-ENG-0456",
    "questionHtml": "<p>Given below are four jumbled sentences.Select the option that gives their correct order.<br>A. However, the rate of the population increase is another important factor to consider.<br>B. This change can be expressed in two ways.<br>C. Growth of population refers to the change in the number of inhabitants of a country.<br>D. First, in terms of absolute numbers and second, in terms of percentage change.</p>\n<ol style=\"list-style-type:upper-alpha\"><li><p>BADC</p></li><li><p>CADB</p></li><li><p>CBDA</p></li><li><p>BDCA</p></li></ol>",
    "options": [
      "<p>BADC</p>",
      "<p>CADB</p>",
      "<p>CBDA</p>",
      "<p>BDCA</p>"
    ],
    "answer": "C",
    "type": "MCQ",
    "subject": "English",
    "subtopic": "Para Jumble",
    "year": null,
    "_source": {
      "sourceKind": "bossxcode-web",
      "examBody": "BossXCode",
      "examName": "BossXCode",
      "pageUrl": "https://pt.bossxcode.unaux.com/play#paper-c2c7d18709c609be",
      "sourceId": "054394a0e45be4d7",
      "originalQNum": "1",
      "topic": "Para Jumble",
      "catalogId": "99bb7cfaaa7dc513"
    }
  },
  {
    "uid": "APT-ENG-0457",
    "questionHtml": "<p>Sentences of a paragraph are given below in jumbled order. Arrange the sentences in<br>the correct order to form a meaningful and coherent paragraph.<br>A. They can help you to decide the right products for you.<br>B. Advertisements can be extremely useful if they are honest.<br>C. Teenagers are especially vulnerable to such advertisements.<br>D. However, some advertisements may be harmful as they try to befool you.</p>\n<ol style=\"list-style-type:upper-alpha\"><li>CDAB</li><li>BADC</li><li>BCAD</li><li>CADB</li></ol>",
    "options": [
      "CDAB",
      "BADC",
      "BCAD",
      "CADB"
    ],
    "answer": "B",
    "type": "MCQ",
    "subject": "English",
    "subtopic": "Para Jumble",
    "year": null,
    "_source": {
      "sourceKind": "bossxcode-web",
      "examBody": "BossXCode",
      "examName": "BossXCode",
      "pageUrl": "https://pt.bossxcode.unaux.com/play#paper-58db70b094c063e3",
      "sourceId": "c158815297315926",
      "originalQNum": "1",
      "topic": "Para Jumble",
      "catalogId": "0353496bb1d7b0f0"
    }
  },
  {
    "uid": "APT-ENG-0458",
    "questionHtml": "<p>Sentences of a paragraph are given below in jumbled order. Arrange the sentences in the right order to form a meaningful and coherent paragraph. <br>A. They stopped at a village on the way to rest and drink water and found the entire village had gathered to watch a weightlifter who was putting on a performance. <br>B. Tenali was very impressed and exclaimed, “You are very strong!” <br>C. With his big arms and bulging muscles, he picked up a 200-kg bag of rice with ease. <br>D. One day Tenali Raman and his wife were on their way to Hampi.</p>\n<ol style=\"list-style-type:upper-alpha\"><li><p>DACB</p></li><li><p>CDAB</p></li><li><p>BDCA</p></li><li><p>DBCA</p></li></ol>",
    "options": [
      "<p>DACB</p>",
      "<p>CDAB</p>",
      "<p>BDCA</p>",
      "<p>DBCA</p>"
    ],
    "answer": "A",
    "type": "MCQ",
    "subject": "English",
    "subtopic": "Para Jumble",
    "year": null,
    "_source": {
      "sourceKind": "bossxcode-web",
      "examBody": "BossXCode",
      "examName": "BossXCode",
      "pageUrl": "https://pt.bossxcode.unaux.com/play#paper-bbf3f6915c76edfb",
      "sourceId": "f1f90f01eb873364",
      "originalQNum": "1",
      "topic": "Para Jumble",
      "catalogId": "b7aa877f2b97f6f0"
    }
  },
  {
    "uid": "APT-ENG-0459",
    "questionHtml": "<p>Sentences of a paragraph are given below in jumbled order. Arrange the sentences in the right order to form a meaningful and coherent paragraph. <br>A. When we got near, we saw it was the steam rising from hot springs.<br>B. We saw in the distance a great column of smoke.<br>C. We wondered if it came from a chimney or a burning house.<br>D. We thought of taking a bath in the hot water.</p>\n<ol style=\"list-style-type:upper-alpha\"><li><p>ACDB</p></li><li><p>ABCD</p></li><li><p>BCAD</p></li><li><p>BCDA</p></li></ol>",
    "options": [
      "<p>ACDB</p>",
      "<p>ABCD</p>",
      "<p>BCAD</p>",
      "<p>BCDA</p>"
    ],
    "answer": "C",
    "type": "MCQ",
    "subject": "English",
    "subtopic": "Para Jumble",
    "year": null,
    "_source": {
      "sourceKind": "bossxcode-web",
      "examBody": "BossXCode",
      "examName": "BossXCode",
      "pageUrl": "https://pt.bossxcode.unaux.com/play#paper-f703404b3f6d37c2",
      "sourceId": "17bece96fea87e15",
      "originalQNum": "1",
      "topic": "Para Jumble",
      "catalogId": "45993ae7db6c903b"
    }
  },
  {
    "uid": "APT-ENG-0460",
    "questionHtml": "<p>Given below are four jumbled sentences. Select the option that gives their correct <br>order. <br>A. Our amusements have little zest if we engage in them in solitude. <br>B. Friendship increases happiness and diminishes misery. <br>C. It doubles our joys and divides our grief. <br>D. When we do well, it is delightful to have friends who are pleased with our success.</p>\n<ol style=\"list-style-type:upper-alpha\"><li>BCDA</li><li>ABDC</li><li>CBAD</li><li>DACB</li></ol>",
    "options": [
      "BCDA",
      "ABDC",
      "CBAD",
      "DACB"
    ],
    "answer": "A",
    "type": "MCQ",
    "subject": "English",
    "subtopic": "Para Jumble",
    "year": null,
    "_source": {
      "sourceKind": "bossxcode-web",
      "examBody": "BossXCode",
      "examName": "BossXCode",
      "pageUrl": "https://pt.bossxcode.unaux.com/play#paper-58db70b094c063e3",
      "sourceId": "807cb5789eb2b89a",
      "originalQNum": "2",
      "topic": "Para Jumble",
      "catalogId": "0353496bb1d7b0f0"
    }
  },
  {
    "uid": "APT-ENG-0461",
    "questionHtml": "<p>Given below are four jumbled sentences.Select the option that gives their correct order.<br>A. However, they ignore the truth that progress and success are proportional to the labor they put in.<br>B. The general human tendency is to find fault in the policies framed by the government.<br>C. They blamed the government for their slow progress, expecting miracles and magical transformation in their life.<br>D. So people openly criticize and condemn the policy makers.</p>\n<ol style=\"list-style-type:upper-alpha\"><li>BDCA</li><li><p>DBAC</p></li><li><p>CDAB</p></li><li><p>ABCD</p></li></ol>",
    "options": [
      "BDCA",
      "<p>DBAC</p>",
      "<p>CDAB</p>",
      "<p>ABCD</p>"
    ],
    "answer": "A",
    "type": "MCQ",
    "subject": "English",
    "subtopic": "Para Jumble",
    "year": null,
    "_source": {
      "sourceKind": "bossxcode-web",
      "examBody": "BossXCode",
      "examName": "BossXCode",
      "pageUrl": "https://pt.bossxcode.unaux.com/play#paper-c2c7d18709c609be",
      "sourceId": "460cd44f7a6d4c20",
      "originalQNum": "2",
      "topic": "Para Jumble",
      "catalogId": "99bb7cfaaa7dc513"
    }
  },
  {
    "uid": "APT-ENG-0462",
    "questionHtml": "<p>Sentences of a paragraph are given below in jumbled order. Arrange the sentences in the right order to form a meaningful and coherent paragraph. <br>A. But the eagle, in wrath, gave the beetle a flap of his wing, and straightaway seized upon the hare and devoured him. <br>B. The beetle therefore interceded with the eagle, begging of him not to kill the poor suppliant, and pleaded with him not to kill so small an animal. <br>C. When the eagle flew away, the beetle flew after him, to learn where his nest was. <br>D. A hare, being pursued by an eagle, took himself for refuge to the nest of a beetle, whom he begged to save him.</p>\n<ol style=\"list-style-type:upper-alpha\"><li><p>DBAC</p></li><li><p>DCAB</p></li><li><p>ACDB</p></li><li><p>CBAD</p></li></ol>",
    "options": [
      "<p>DBAC</p>",
      "<p>DCAB</p>",
      "<p>ACDB</p>",
      "<p>CBAD</p>"
    ],
    "answer": "A",
    "type": "MCQ",
    "subject": "English",
    "subtopic": "Para Jumble",
    "year": null,
    "_source": {
      "sourceKind": "bossxcode-web",
      "examBody": "BossXCode",
      "examName": "BossXCode",
      "pageUrl": "https://pt.bossxcode.unaux.com/play#paper-f703404b3f6d37c2",
      "sourceId": "df20b307bde294ea",
      "originalQNum": "2",
      "topic": "Para Jumble",
      "catalogId": "45993ae7db6c903b"
    }
  },
  {
    "uid": "APT-ENG-0463",
    "questionHtml": "<p>Sentences of a paragraph are given below in jumbled order. Arrange the sentences in the right order to form a meaningful and coherent paragraph. <br>A. Shopkeeper: “Here, I have packed them all.” <br>B. Mala: “Please give me a packet of balloons, two packets of streamers, and some candles.” <br>C. Shopkeeper: “Since we are offering some discount on the balloons, you need to pay only thirty rupees.” <br>D. Mala: “How much do I need to pay?”</p>\n<ol style=\"list-style-type:upper-alpha\"><li><p>CDAB</p></li><li><p>ABCD</p></li><li><p>DABC</p></li><li><p>BADC</p></li></ol>",
    "options": [
      "<p>CDAB</p>",
      "<p>ABCD</p>",
      "<p>DABC</p>",
      "<p>BADC</p>"
    ],
    "answer": "D",
    "type": "MCQ",
    "subject": "English",
    "subtopic": "Para Jumble",
    "year": null,
    "_source": {
      "sourceKind": "bossxcode-web",
      "examBody": "BossXCode",
      "examName": "BossXCode",
      "pageUrl": "https://pt.bossxcode.unaux.com/play#paper-bbf3f6915c76edfb",
      "sourceId": "18ac2cd2a82b0e81",
      "originalQNum": "2",
      "topic": "Para Jumble",
      "catalogId": "b7aa877f2b97f6f0"
    }
  },
  {
    "uid": "APT-ENG-0464",
    "questionHtml": "<p>Given below are four jumbled sentences.Select the option that gives their correct order.<br>A. Can I borrow your camera?<br>B. I will give it back to you next week.<br>C. I am going to jungle safari tomorrow.<br>D. My friend told me that jungle is beautiful in these days.</p>\n<ol style=\"list-style-type:upper-alpha\"><li><p>CDAB</p></li><li><p>BACD</p></li><li><p>ADBC</p></li><li><p>CADB</p></li></ol>",
    "options": [
      "<p>CDAB</p>",
      "<p>BACD</p>",
      "<p>ADBC</p>",
      "<p>CADB</p>"
    ],
    "answer": "A",
    "type": "MCQ",
    "subject": "English",
    "subtopic": "Para Jumble",
    "year": null,
    "_source": {
      "sourceKind": "bossxcode-web",
      "examBody": "BossXCode",
      "examName": "BossXCode",
      "pageUrl": "https://pt.bossxcode.unaux.com/play#paper-c2c7d18709c609be",
      "sourceId": "a2ec578aba364d4a",
      "originalQNum": "3",
      "topic": "Para Jumble",
      "catalogId": "99bb7cfaaa7dc513"
    }
  },
  {
    "uid": "APT-ENG-0465",
    "questionHtml": "<p>Sentences of a paragraph are given below in jumbled order. Arrange the sentences in the correct order to form a meaningful and coherent paragraph. <br>A. However, when areas in Leh began to experience water shortages, life didn’t grind <br>to a halt. <br>B. Ladakh is a cold desert with a low average annual rainfall. <br>C. Thus, glaciers have been the main source of water for the people. <br>D. This was because Chewang Norphel, a retired civil engineer came up with the idea of artificial glaciers.</p>\n<ol style=\"list-style-type:upper-alpha\"><li>CBDA</li><li>BCAD</li><li>DABC</li><li>BCDA</li></ol>",
    "options": [
      "CBDA",
      "BCAD",
      "DABC",
      "BCDA"
    ],
    "answer": "B",
    "type": "MCQ",
    "subject": "English",
    "subtopic": "Para Jumble",
    "year": null,
    "_source": {
      "sourceKind": "bossxcode-web",
      "examBody": "BossXCode",
      "examName": "BossXCode",
      "pageUrl": "https://pt.bossxcode.unaux.com/play#paper-58db70b094c063e3",
      "sourceId": "7c2733b8f48b5bab",
      "originalQNum": "3",
      "topic": "Para Jumble",
      "catalogId": "0353496bb1d7b0f0"
    }
  },
  {
    "uid": "APT-ENG-0466",
    "questionHtml": "<p>Sentences of a paragraph are given below in jumbled order. Arrange the sentences in the right order to form a meaningful and coherent paragraph. <br>A. The festival is named after the Indian Hornbill. <br>B. The Hornbill festival is the most anticipated cultural carnival of this state.<br>C. Located in Northeast India, Nagaland is a very beautiful and an ethnically diverse state. <br>D. The Hornbill is often displayed on the traditional tribal headgears worn during Naga festivals.</p>\n<ol style=\"list-style-type:upper-alpha\"><li><p>ABCD</p></li><li><p>BCAD</p></li><li><p>ACBD</p></li><li><p>CBAD</p></li></ol>",
    "options": [
      "<p>ABCD</p>",
      "<p>BCAD</p>",
      "<p>ACBD</p>",
      "<p>CBAD</p>"
    ],
    "answer": "D",
    "type": "MCQ",
    "subject": "English",
    "subtopic": "Para Jumble",
    "year": null,
    "_source": {
      "sourceKind": "bossxcode-web",
      "examBody": "BossXCode",
      "examName": "BossXCode",
      "pageUrl": "https://pt.bossxcode.unaux.com/play#paper-bbf3f6915c76edfb",
      "sourceId": "7cd1c04f16f26da4",
      "originalQNum": "3",
      "topic": "Para Jumble",
      "catalogId": "b7aa877f2b97f6f0"
    }
  },
  {
    "uid": "APT-ENG-0467",
    "questionHtml": "<p>Sentences of a paragraph are given below in jumbled order. Arrange the sentences in the right order to form a meaningful and coherent paragraph. <br>A. “Excellently well,” said she; “we have everything that we want; I have but one prayer, that we may have a heavy storm of rain to water our plants.” <br>B. A man who had two daughters married one to a gardener and the other to a potter. <br>C. Off he went to the potter's home and asked his other daughter how matters were with her. <br>D. After a while he paid a visit to the gardener's home and asked his daughter how she was, and how it fared with her.</p>\n<ol style=\"list-style-type:upper-alpha\"><li><p>BDAC</p></li><li><p>ACDB</p></li><li><p>BCDA</p></li><li><p>DCAB</p></li></ol>",
    "options": [
      "<p>BDAC</p>",
      "<p>ACDB</p>",
      "<p>BCDA</p>",
      "<p>DCAB</p>"
    ],
    "answer": "A",
    "type": "MCQ",
    "subject": "English",
    "subtopic": "Para Jumble",
    "year": null,
    "_source": {
      "sourceKind": "bossxcode-web",
      "examBody": "BossXCode",
      "examName": "BossXCode",
      "pageUrl": "https://pt.bossxcode.unaux.com/play#paper-f703404b3f6d37c2",
      "sourceId": "5f6b3df851ec30e1",
      "originalQNum": "3",
      "topic": "Para Jumble",
      "catalogId": "45993ae7db6c903b"
    }
  },
  {
    "uid": "APT-ENG-0468",
    "questionHtml": "<p>Given below are four jumbled sentences.Select the option that gives their correct order.<br>A. Nevertheless, sound health, economic security and mental satisfaction are desired by all<br>B. A change that is conducive to happiness may be termed as progress.<br>C. But different people find happiness in different things.<br>D. So, if a change contributes to the growth of these factors, it is progress.</p>\n<ol style=\"list-style-type:upper-alpha\"><li><p>BDCA</p></li><li><p>ABCD</p></li><li><p>BCAD</p></li><li><p>DBCA</p></li></ol>",
    "options": [
      "<p>BDCA</p>",
      "<p>ABCD</p>",
      "<p>BCAD</p>",
      "<p>DBCA</p>"
    ],
    "answer": "C",
    "type": "MCQ",
    "subject": "English",
    "subtopic": "Para Jumble",
    "year": null,
    "_source": {
      "sourceKind": "bossxcode-web",
      "examBody": "BossXCode",
      "examName": "BossXCode",
      "pageUrl": "https://pt.bossxcode.unaux.com/play#paper-c2c7d18709c609be",
      "sourceId": "9431c5b93c675c0c",
      "originalQNum": "4",
      "topic": "Para Jumble",
      "catalogId": "99bb7cfaaa7dc513"
    }
  },
  {
    "uid": "APT-ENG-0469",
    "questionHtml": "<p>Sentences of a paragraph are given below in jumbled order. Arrange the sentences in the correct order to form a meaningful and coherent paragraph. <br>A. The interest rates offered depends on the bank, deposit amount and the tenure you choose. <br>B. It not only helps you to save money but also helps you to earn a substantial interest on it. <br>C. One of the best ways to secure your money is by investing in fixed deposits. <br>D. Under the fixed deposit scheme, the depositor deposits the money only once at the time of opening the account.</p>\n<ol style=\"list-style-type:upper-alpha\"><li><p>CDBA</p></li><li><p>ADCB</p></li><li><p>ACBD</p></li><li><p>CABD</p></li></ol>",
    "options": [
      "<p>CDBA</p>",
      "<p>ADCB</p>",
      "<p>ACBD</p>",
      "<p>CABD</p>"
    ],
    "answer": "A",
    "type": "MCQ",
    "subject": "English",
    "subtopic": "Para Jumble",
    "year": null,
    "_source": {
      "sourceKind": "bossxcode-web",
      "examBody": "BossXCode",
      "examName": "BossXCode",
      "pageUrl": "https://pt.bossxcode.unaux.com/play#paper-58db70b094c063e3",
      "sourceId": "b333819ca5db8edc",
      "originalQNum": "4",
      "topic": "Para Jumble",
      "catalogId": "0353496bb1d7b0f0"
    }
  },
  {
    "uid": "APT-ENG-0470",
    "questionHtml": "<p>Sentences of a paragraph are given below in jumbled order. Arrange the sentences in the right order to form a meaningful and coherent paragraph. <br>A. When it was time to divide the spoils, the lion took one portion for his title as king of the forest.<br>B. He took another portion because he was a partner, and yet another because he was the strongest.<br>C. He took the last portion because an accident would befall anyone who laid a paw upon it. <br>D. Once a lion went hunting with three other beasts.</p>\n<ol style=\"list-style-type:upper-alpha\"><li>DCBA</li><li>DABC</li><li>CABD</li><li>BDCA</li></ol>",
    "options": [
      "DCBA",
      "DABC",
      "CABD",
      "BDCA"
    ],
    "answer": "B",
    "type": "MCQ",
    "subject": "English",
    "subtopic": "Para Jumble",
    "year": null,
    "_source": {
      "sourceKind": "bossxcode-web",
      "examBody": "BossXCode",
      "examName": "BossXCode",
      "pageUrl": "https://pt.bossxcode.unaux.com/play#paper-bbf3f6915c76edfb",
      "sourceId": "b64c9295cafab590",
      "originalQNum": "4",
      "topic": "Para Jumble",
      "catalogId": "b7aa877f2b97f6f0"
    }
  },
  {
    "uid": "APT-ENG-0471",
    "questionHtml": "<p>Sentences of a paragraph are given below in jumbled order. Arrange the sentences in the right order to form a meaningful and coherent paragraph. <br>A. While India is home to 75 per cent of the tigers in the world, the Global Tiger Day, as it is also known - sees awareness events organised in the country, as well as in neighbouring Bangladesh and Nepal. <br>B. Its primary objective is to preserve the natural habitat of the tiger. <br>C. International Tiger Day was initiated in 2010, at the Saint Petersburg Tiger Summit. <br>D. This annual event observed on 29 July, aims to create awareness on tiger conservation.</p>\n<ol style=\"list-style-type:upper-alpha\"><li><p>CDBA</p></li><li><p>BACD</p></li><li><p>CABD</p></li><li><p>DCBA</p></li></ol>",
    "options": [
      "<p>CDBA</p>",
      "<p>BACD</p>",
      "<p>CABD</p>",
      "<p>DCBA</p>"
    ],
    "answer": "A",
    "type": "MCQ",
    "subject": "English",
    "subtopic": "Para Jumble",
    "year": null,
    "_source": {
      "sourceKind": "bossxcode-web",
      "examBody": "BossXCode",
      "examName": "BossXCode",
      "pageUrl": "https://pt.bossxcode.unaux.com/play#paper-f703404b3f6d37c2",
      "sourceId": "e3a4cef40374f98f",
      "originalQNum": "4",
      "topic": "Para Jumble",
      "catalogId": "45993ae7db6c903b"
    }
  },
  {
    "uid": "APT-ENG-0472",
    "questionHtml": "<p>Given below are four jumbled sentences.Select the option that gives their correct order.<br>A. It requires physical endurance, which can be built with training and exercise.<br>B. Truly strong personalities meet challenges of life bravely and face hardships with equanimity.<br>C. However, the strength of character is a personality trait or a quality.<br>D. Physical strength  is the ability to cope with a physically challenging task.</p>\n<ol style=\"list-style-type:upper-alpha\"><li>BACD</li><li>CBAD</li><li>DACB</li><li>DBCA</li></ol>",
    "options": [
      "BACD",
      "CBAD",
      "DACB",
      "DBCA"
    ],
    "answer": "C",
    "type": "MCQ",
    "subject": "English",
    "subtopic": "Para Jumble",
    "year": null,
    "_source": {
      "sourceKind": "bossxcode-web",
      "examBody": "BossXCode",
      "examName": "BossXCode",
      "pageUrl": "https://pt.bossxcode.unaux.com/play#paper-c2c7d18709c609be",
      "sourceId": "9b71ffc6c1eb3b48",
      "originalQNum": "5",
      "topic": "Para Jumble",
      "catalogId": "99bb7cfaaa7dc513"
    }
  },
  {
    "uid": "APT-ENG-0473",
    "questionHtml": "<p>Given below are four sentences which are jumbled. Pick the option that gives their correct order. <br>A. Schools are closed for the Christmas and winter break at this time of the year. <br>B. Christmas and New Year are the time of the year to celebrate. <br>C. All over the city, winter carnivals and Christmas bazaars lend fun and warmth in the cold. <br>D. For the second time in a row, we are likely to see restrained celebrations for fear of the pandemic raising its ugly head again.</p>\n<ol style=\"list-style-type:upper-alpha\"><li>BADC</li><li>BACD</li><li>ABCD</li><li>BCDA</li></ol>",
    "options": [
      "BADC",
      "BACD",
      "ABCD",
      "BCDA"
    ],
    "answer": "B",
    "type": "MCQ",
    "subject": "English",
    "subtopic": "Para Jumble",
    "year": null,
    "_source": {
      "sourceKind": "bossxcode-web",
      "examBody": "BossXCode",
      "examName": "BossXCode",
      "pageUrl": "https://pt.bossxcode.unaux.com/play#paper-58db70b094c063e3",
      "sourceId": "043b6151a55b0cc3",
      "originalQNum": "5",
      "topic": "Para Jumble",
      "catalogId": "0353496bb1d7b0f0"
    }
  },
  {
    "uid": "APT-ENG-0474",
    "questionHtml": "<p>Sentences of a paragraph are given below in jumbled order. Arrange the sentences in the right order to form a meaningful and coherent paragraph. <br>A. According to his hypothesis, now known as the neuron theory, each nerve cell communicates with others through contiguity rather than continuity. <br>B. The watershed of all studies of the nervous system was an observation made in 1889 by Spanish scientist Santiago Ramón y Cajal. <br>C. It has since been proved that Cajal’s theory is not universally true, but his central idea has remained an accurate guiding principle for all further study. <br>D. That is, communication between adjacent but separate cells must take place across the space and barriers separating them.</p>\n<ol style=\"list-style-type:upper-alpha\"><li>BCDA</li><li>ADCB</li><li>BADC</li><li>CDAB</li></ol>",
    "options": [
      "BCDA",
      "ADCB",
      "BADC",
      "CDAB"
    ],
    "answer": "C",
    "type": "MCQ",
    "subject": "English",
    "subtopic": "Para Jumble",
    "year": null,
    "_source": {
      "sourceKind": "bossxcode-web",
      "examBody": "BossXCode",
      "examName": "BossXCode",
      "pageUrl": "https://pt.bossxcode.unaux.com/play#paper-bbf3f6915c76edfb",
      "sourceId": "b6e5d41380828f34",
      "originalQNum": "5",
      "topic": "Para Jumble",
      "catalogId": "b7aa877f2b97f6f0"
    }
  },
  {
    "uid": "APT-ENG-0475",
    "questionHtml": "<p>Sentences of a paragraph are given below in jumbled order. Arrange the sentences in the right order to form a meaningful and coherent paragraph. <br>A. At length the olive tree's branches broke with the snow's weight, at once despoiling it of its beauty and killing the tree. <br>B. A shower of snow fell upon them and, finding the olive full of foliage, it settled upon its branches. <br>C. Finding the fig tree without leaves, the snow fell through the branches to the ground and did not injure it at all. <br>D. The olive tree ridiculed the fig tree because, while she was green all the year round, the fig tree changed its leaves with the seasons.</p>\n<ol style=\"list-style-type:upper-alpha\"><li><p>DBAC</p></li><li><p>ABCD</p></li><li><p>ACBD</p></li><li><p>DACB</p></li></ol>",
    "options": [
      "<p>DBAC</p>",
      "<p>ABCD</p>",
      "<p>ACBD</p>",
      "<p>DACB</p>"
    ],
    "answer": "A",
    "type": "MCQ",
    "subject": "English",
    "subtopic": "Para Jumble",
    "year": null,
    "_source": {
      "sourceKind": "bossxcode-web",
      "examBody": "BossXCode",
      "examName": "BossXCode",
      "pageUrl": "https://pt.bossxcode.unaux.com/play#paper-f703404b3f6d37c2",
      "sourceId": "5d053fcce0790b38",
      "originalQNum": "5",
      "topic": "Para Jumble",
      "catalogId": "45993ae7db6c903b"
    }
  },
  {
    "uid": "APT-ENG-0476",
    "questionHtml": "<p>Given below are four jumbled sentences.Select the option that gives their correct order.<br>A. He then called out to the people but by then only a red glow was visible in the sky.<br>B. At first, he thought it was a stuck kite.<br>C. Bheema was visiting his fields when he spotted a rising disc shaped object.<br>D. But it started rising higher and emitted light, he was shocked.</p>\n<ol style=\"list-style-type:upper-alpha\"><li><p>BACD</p></li><li><p>CDAB</p></li><li><p>BDAC</p></li><li><p>CBDA</p></li></ol>",
    "options": [
      "<p>BACD</p>",
      "<p>CDAB</p>",
      "<p>BDAC</p>",
      "<p>CBDA</p>"
    ],
    "answer": "D",
    "type": "MCQ",
    "subject": "English",
    "subtopic": "Para Jumble",
    "year": null,
    "_source": {
      "sourceKind": "bossxcode-web",
      "examBody": "BossXCode",
      "examName": "BossXCode",
      "pageUrl": "https://pt.bossxcode.unaux.com/play#paper-c2c7d18709c609be",
      "sourceId": "1927f0978d7bb872",
      "originalQNum": "6",
      "topic": "Para Jumble",
      "catalogId": "99bb7cfaaa7dc513"
    }
  },
  {
    "uid": "APT-ENG-0477",
    "questionHtml": "<p>Given below are four sentences which are jumbled. Pick the option that gives their correct order. <br>A. It is a Park quite different from any other we have seen. <br>B. One difference is that it is made from nearly 250 tons of scrap. <br>C. Another difference is that it is powered by wind and solar energy <br>D. A new Park called Bharat Darshan Park has been thrown open to the public in New Delhi.</p>\n<ol style=\"list-style-type:upper-alpha\"><li>ACDB</li><li>DABC</li><li>BACD</li><li>DBCA</li></ol>",
    "options": [
      "ACDB",
      "DABC",
      "BACD",
      "DBCA"
    ],
    "answer": "B",
    "type": "MCQ",
    "subject": "English",
    "subtopic": "Para Jumble",
    "year": null,
    "_source": {
      "sourceKind": "bossxcode-web",
      "examBody": "BossXCode",
      "examName": "BossXCode",
      "pageUrl": "https://pt.bossxcode.unaux.com/play#paper-58db70b094c063e3",
      "sourceId": "87929e532cf84aca",
      "originalQNum": "6",
      "topic": "Para Jumble",
      "catalogId": "0353496bb1d7b0f0"
    }
  },
  {
    "uid": "APT-ENG-0478",
    "questionHtml": "<p>Sentences of a paragraph are given below in jumbled order. Arrange the sentences in the right order to form a meaningful and coherent paragraph. <br>A. Dad: “Yes, tell me.” <br>B. Laxmi: “Dad, I need to speak to you.” <br>C. Dad: “I think you are still too young for it.” <br>D. Laxmi: “Please buy me a scooter.”</p>\n<ol style=\"list-style-type:upper-alpha\"><li><p>DCBA</p></li><li><p>ABDC</p></li><li><p>BADC</p></li><li><p>BCDA</p></li></ol>",
    "options": [
      "<p>DCBA</p>",
      "<p>ABDC</p>",
      "<p>BADC</p>",
      "<p>BCDA</p>"
    ],
    "answer": "C",
    "type": "MCQ",
    "subject": "English",
    "subtopic": "Para Jumble",
    "year": null,
    "_source": {
      "sourceKind": "bossxcode-web",
      "examBody": "BossXCode",
      "examName": "BossXCode",
      "pageUrl": "https://pt.bossxcode.unaux.com/play#paper-bbf3f6915c76edfb",
      "sourceId": "c713d468630f1ed8",
      "originalQNum": "6",
      "topic": "Para Jumble",
      "catalogId": "b7aa877f2b97f6f0"
    }
  },
  {
    "uid": "APT-ENG-0479",
    "questionHtml": "<p>Sentences of a paragraph are given below in jumbled order. Arrange the sentences in the right order to form a meaningful and coherent paragraph. <br>A. When he reached his town, he went to his house and knocked at the door. <br>B. A man went away from his home. <br>C. Disappointed, he decided to take it himself. <br>D. One day he wrote a letter to his family, but could not find any one to take the letter to his town.</p>\n<ol style=\"list-style-type:upper-alpha\"><li><p>DACB</p></li><li><p>BDCA</p></li><li><p>CBAD</p></li><li><p>ABCD</p></li></ol>",
    "options": [
      "<p>DACB</p>",
      "<p>BDCA</p>",
      "<p>CBAD</p>",
      "<p>ABCD</p>"
    ],
    "answer": "B",
    "type": "MCQ",
    "subject": "English",
    "subtopic": "Para Jumble",
    "year": null,
    "_source": {
      "sourceKind": "bossxcode-web",
      "examBody": "BossXCode",
      "examName": "BossXCode",
      "pageUrl": "https://pt.bossxcode.unaux.com/play#paper-f703404b3f6d37c2",
      "sourceId": "c9e7a4cd352feecd",
      "originalQNum": "6",
      "topic": "Para Jumble",
      "catalogId": "45993ae7db6c903b"
    }
  },
  {
    "uid": "APT-ENG-0480",
    "questionHtml": "<p>Arrange the statements in the correct order to make a meaningful paragraph.<br>A. But, in developed societies, the childhood and adolescence is extended.<br>B. In rural communities, the customs are more uniform.<br>C. This provides more opportunities for education and character development.<br>D. The practices of child rearing vary from culture to culture.</p>\n<ol style=\"list-style-type:upper-alpha\"><li>DABC</li><li>BADC</li><li>DBAC</li><li>BCDA</li></ol>",
    "options": [
      "DABC",
      "BADC",
      "DBAC",
      "BCDA"
    ],
    "answer": "C",
    "type": "MCQ",
    "subject": "English",
    "subtopic": "Para Jumble",
    "year": null,
    "_source": {
      "sourceKind": "bossxcode-web",
      "examBody": "BossXCode",
      "examName": "BossXCode",
      "pageUrl": "https://pt.bossxcode.unaux.com/play#paper-58db70b094c063e3",
      "sourceId": "8210470457763593",
      "originalQNum": "7",
      "topic": "Para Jumble",
      "catalogId": "0353496bb1d7b0f0"
    }
  },
  {
    "uid": "APT-ENG-0481",
    "questionHtml": "<p>Given below are four jumbled sentences.Select the option that gives their correct order.<br>A. Eventually, she overcame adversities and achieved success.<br>B. She engaged herself in 'earn while you learn', finance scheme in her college.<br>C. She needed financial support to complete her graduation.<br>D. Rama was a very poor girl.</p>\n<ol style=\"list-style-type:upper-alpha\"><li><p>ABCD</p></li><li><p>ADCB</p></li><li><p>DCBA</p></li><li><p>CBDA</p></li></ol>",
    "options": [
      "<p>ABCD</p>",
      "<p>ADCB</p>",
      "<p>DCBA</p>",
      "<p>CBDA</p>"
    ],
    "answer": "C",
    "type": "MCQ",
    "subject": "English",
    "subtopic": "Para Jumble",
    "year": null,
    "_source": {
      "sourceKind": "bossxcode-web",
      "examBody": "BossXCode",
      "examName": "BossXCode",
      "pageUrl": "https://pt.bossxcode.unaux.com/play#paper-c2c7d18709c609be",
      "sourceId": "62f2f8d78dae7ae2",
      "originalQNum": "7",
      "topic": "Para Jumble",
      "catalogId": "99bb7cfaaa7dc513"
    }
  },
  {
    "uid": "APT-ENG-0482",
    "questionHtml": "<p>Sentences of a paragraph are given below in jumbled order. Arrange the sentences in the right order to form a meaningful and coherent paragraph. <br>A. Indeed, polymers such as regenerated cellulose, which have become familiar household materials under the trade names rayon and nylon, are also made into numerous non-fibre products, ranging from cellophane envelope windows to clear plastic soft-drink bottles. <br>B. The chemical compounds from which man-made fibres are produced are known as polymers, a class of compounds characterised by long, chain-like molecules of great size and molecular weight. <br>C. As fibres, these materials are prized for their strength, toughness, resistance to heat and mildew, and ability to hold a pressed form. <br>D. Many of the polymers that constitute man-made fibres are the same as or similar to compounds that make up plastics, rubbers, adhesives and surface coatings.</p>\n<ol style=\"list-style-type:upper-alpha\"><li><p>CBAD</p></li><li><p>BCDA</p></li><li><p>BDAC</p></li><li><p>ACDB</p></li></ol>",
    "options": [
      "<p>CBAD</p>",
      "<p>BCDA</p>",
      "<p>BDAC</p>",
      "<p>ACDB</p>"
    ],
    "answer": "B",
    "type": "MCQ",
    "subject": "English",
    "subtopic": "Para Jumble",
    "year": null,
    "_source": {
      "sourceKind": "bossxcode-web",
      "examBody": "BossXCode",
      "examName": "BossXCode",
      "pageUrl": "https://pt.bossxcode.unaux.com/play#paper-bbf3f6915c76edfb",
      "sourceId": "2947ccc690884546",
      "originalQNum": "7",
      "topic": "Para Jumble",
      "catalogId": "b7aa877f2b97f6f0"
    }
  },
  {
    "uid": "APT-ENG-0483",
    "questionHtml": "<p>Sentences of a paragraph are given below in jumbled order. Arrange the sentences in the right order to form a meaningful and coherent paragraph. <br>A. Then I took him by the hand and led him across the street. <br>B. I was going to the market when I saw a blind man trying to cross the street. <br>C. He expressed his gratitude with folded hands. <br>D. I walked across to the blind man.</p>\n<ol style=\"list-style-type:upper-alpha\"><li>ABCD</li><li>CBDA</li><li>BDAC</li><li>DABC</li></ol>",
    "options": [
      "ABCD",
      "CBDA",
      "BDAC",
      "DABC"
    ],
    "answer": "C",
    "type": "MCQ",
    "subject": "English",
    "subtopic": "Para Jumble",
    "year": null,
    "_source": {
      "sourceKind": "bossxcode-web",
      "examBody": "BossXCode",
      "examName": "BossXCode",
      "pageUrl": "https://pt.bossxcode.unaux.com/play#paper-f703404b3f6d37c2",
      "sourceId": "c687e9b7cd11b236",
      "originalQNum": "7",
      "topic": "Para Jumble",
      "catalogId": "45993ae7db6c903b"
    }
  },
  {
    "uid": "APT-ENG-0484",
    "questionHtml": "<p>Given below are four jumbled sentences. Select the option that gives their correct order. <br>A. Finally, it can be termed as the channel for all trade, and what is more important, of all ideas. <br>B. It also provides framework to all economic development. <br>C. It is the road which determines the site of many cities and the growth and nourishment of all.<br>D. The road is one of the great fundamental institutions of mankind.</p>\n<ol style=\"list-style-type:upper-alpha\"><li><p>CABD</p></li><li><p>DCBA</p></li><li><p>BDAC</p></li><li><p>DBAC</p></li></ol>",
    "options": [
      "<p>CABD</p>",
      "<p>DCBA</p>",
      "<p>BDAC</p>",
      "<p>DBAC</p>"
    ],
    "answer": "B",
    "type": "MCQ",
    "subject": "English",
    "subtopic": "Para Jumble",
    "year": null,
    "_source": {
      "sourceKind": "bossxcode-web",
      "examBody": "BossXCode",
      "examName": "BossXCode",
      "pageUrl": "https://pt.bossxcode.unaux.com/play#paper-58db70b094c063e3",
      "sourceId": "64bc2d3da734ec59",
      "originalQNum": "8",
      "topic": "Para Jumble",
      "catalogId": "0353496bb1d7b0f0"
    }
  },
  {
    "uid": "APT-ENG-0485",
    "questionHtml": "<p>Given below are four jumbled sentences.Select the option that gives their correct order.<br>A. &quot;We are going to the market&quot;,declared Reetu and Geetu.<br>B. &quot;Where are you going?&quot; the father asked.<br>C. &quot;Take your umbrella, it is going to rain&quot;, the mother said.<br>D. &quot;Yes,definitely. We will,&quot; replied the two.</p>\n<ol style=\"list-style-type:upper-alpha\"><li>ABDC</li><li>DCAB</li><li>BACD</li><li>BCDA</li></ol>",
    "options": [
      "ABDC",
      "DCAB",
      "BACD",
      "BCDA"
    ],
    "answer": "C",
    "type": "MCQ",
    "subject": "English",
    "subtopic": "Para Jumble",
    "year": null,
    "_source": {
      "sourceKind": "bossxcode-web",
      "examBody": "BossXCode",
      "examName": "BossXCode",
      "pageUrl": "https://pt.bossxcode.unaux.com/play#paper-c2c7d18709c609be",
      "sourceId": "9c950e279a6397ea",
      "originalQNum": "8",
      "topic": "Para Jumble",
      "catalogId": "99bb7cfaaa7dc513"
    }
  },
  {
    "uid": "APT-ENG-0486",
    "questionHtml": "<p>Sentences of a paragraph are given below in jumbled order. Arrange the sentences in the right order to form a meaningful and coherent paragraph. <br>A. He was in the habit of stealing food from others. <br>B. One night, the villagers decided to teach him a lesson and kept only rotten food in their kitchen. <br>C. The culprit ended up eating the rotten food and fell sick. <br>D. Once upon a time, there lived a man in a village.</p>\n<ol style=\"list-style-type:upper-alpha\"><li><p>ABDC</p></li><li><p>BACD</p></li><li><p>DABC</p></li><li><p>ACDB</p></li></ol>",
    "options": [
      "<p>ABDC</p>",
      "<p>BACD</p>",
      "<p>DABC</p>",
      "<p>ACDB</p>"
    ],
    "answer": "C",
    "type": "MCQ",
    "subject": "English",
    "subtopic": "Para Jumble",
    "year": null,
    "_source": {
      "sourceKind": "bossxcode-web",
      "examBody": "BossXCode",
      "examName": "BossXCode",
      "pageUrl": "https://pt.bossxcode.unaux.com/play#paper-bbf3f6915c76edfb",
      "sourceId": "196e845b6615d645",
      "originalQNum": "8",
      "topic": "Para Jumble",
      "catalogId": "b7aa877f2b97f6f0"
    }
  },
  {
    "uid": "APT-ENG-0487",
    "questionHtml": "<p>Sentences of a paragraph are given below in jumbled order. Arrange the sentences in the right order to form a meaningful and coherent paragraph. <br>A. This invention has helped us to heal wounds caused by bacteria. <br>B. Penicillin is one of the most useful drugs man has invented. <br>C. In the beginning however, very few people knew of this discovery and its use. <br>D. Its use has saved the lives of hundreds of thousands of soldiers.</p>\n<ol style=\"list-style-type:upper-alpha\"><li>ABCD</li><li>CABD</li><li>BADC</li><li>DCBA</li></ol>",
    "options": [
      "ABCD",
      "CABD",
      "BADC",
      "DCBA"
    ],
    "answer": "C",
    "type": "MCQ",
    "subject": "English",
    "subtopic": "Para Jumble",
    "year": null,
    "_source": {
      "sourceKind": "bossxcode-web",
      "examBody": "BossXCode",
      "examName": "BossXCode",
      "pageUrl": "https://pt.bossxcode.unaux.com/play#paper-f703404b3f6d37c2",
      "sourceId": "7c6534cd91e22f54",
      "originalQNum": "8",
      "topic": "Para Jumble",
      "catalogId": "45993ae7db6c903b"
    }
  },
  {
    "uid": "APT-ENG-0488",
    "questionHtml": "<p>Select the most appropriate sequence from the given options to make a meaningful paragraph from jumbled sentences.<br>A. They can then purchase them on subsidized rates with additional loan facilities.<br>B. It will import technologically advanced medical instruments and provide them to entrepreneurs.<br>C. The Indian Government has announced certain facilities in the budget session.<br>D. This will help in strengthening the economic condition of entrepreneur.</p>\n<ol style=\"list-style-type:upper-alpha\"><li>BDCA</li><li>DADB</li><li>CBAD</li><li>DCAB</li></ol>",
    "options": [
      "BDCA",
      "DADB",
      "CBAD",
      "DCAB"
    ],
    "answer": "C",
    "type": "MCQ",
    "subject": "English",
    "subtopic": "Para Jumble",
    "year": null,
    "_source": {
      "sourceKind": "bossxcode-web",
      "examBody": "BossXCode",
      "examName": "BossXCode",
      "pageUrl": "https://pt.bossxcode.unaux.com/play#paper-c2c7d18709c609be",
      "sourceId": "13813ea66cd2cc49",
      "originalQNum": "9",
      "topic": "Para Jumble",
      "catalogId": "99bb7cfaaa7dc513"
    }
  },
  {
    "uid": "APT-ENG-0489",
    "questionHtml": "<p>Sentences of a paragraph are given below in jumbled order. Arrange the sentences in <br>the correct order to form a meaningful and coherent paragraph. <br>A. Firstly, it provides air for respiration, serves the sense of smell and conditions the <br>air by filtering, warming and moistening it. <br>B. The nose is the prominent structure between the eyes that serves as the entrance to <br>the respiratory tract. <br>C. For inhalation it has two cavities, separated from one another by a wall <br>of cartilage called the septum. <br>D. Apart from filtering the air, it also cleans itself of foreign debris extracted from <br>Inhalations.</p>\n<ol style=\"list-style-type:upper-alpha\"><li>BACD</li><li>ACDB</li><li>BADC</li><li>DBCA</li></ol>",
    "options": [
      "BACD",
      "ACDB",
      "BADC",
      "DBCA"
    ],
    "answer": "C",
    "type": "MCQ",
    "subject": "English",
    "subtopic": "Para Jumble",
    "year": null,
    "_source": {
      "sourceKind": "bossxcode-web",
      "examBody": "BossXCode",
      "examName": "BossXCode",
      "pageUrl": "https://pt.bossxcode.unaux.com/play#paper-58db70b094c063e3",
      "sourceId": "aa9e03c5c643ea08",
      "originalQNum": "9",
      "topic": "Para Jumble",
      "catalogId": "0353496bb1d7b0f0"
    }
  },
  {
    "uid": "APT-ENG-0490",
    "questionHtml": "<p>Sentences of a paragraph are given below in jumbled order. Arrange the sentences in the right order to form a meaningful and coherent paragraph. <br>A. There lived a foolish king in a large kingdom. <br>B. He thought that it will be a good joke. <br>C. He did not realise that what he thought of as a joke would cost him heavily. <br>D. The king once decided to throw all his ministers in prison for a day.</p>\n<ol style=\"list-style-type:upper-alpha\"><li><p>ABCD</p></li><li><p>ACBD</p></li><li><p>DABC</p></li><li><p>ADBC</p></li></ol>",
    "options": [
      "<p>ABCD</p>",
      "<p>ACBD</p>",
      "<p>DABC</p>",
      "<p>ADBC</p>"
    ],
    "answer": "D",
    "type": "MCQ",
    "subject": "English",
    "subtopic": "Para Jumble",
    "year": null,
    "_source": {
      "sourceKind": "bossxcode-web",
      "examBody": "BossXCode",
      "examName": "BossXCode",
      "pageUrl": "https://pt.bossxcode.unaux.com/play#paper-bbf3f6915c76edfb",
      "sourceId": "a73c0ced3485d672",
      "originalQNum": "9",
      "topic": "Para Jumble",
      "catalogId": "b7aa877f2b97f6f0"
    }
  },
  {
    "uid": "APT-ENG-0491",
    "questionHtml": "<p>Sentences of a paragraph are given below in jumbled order. Arrange the sentences in the right order to form a meaningful and coherent paragraph. <br>A. This awareness has motivated everyone to go for physical exercises. <br>B. These days people are more aware of their health. <br>C. In addition to physical exercises, some prefer taking health supplements too. <br>D. It is advisable, but one should consult a trainer/doctor before consuming health supplements.</p>\n<ol style=\"list-style-type:upper-alpha\"><li><p>DBCA</p></li><li><p>ADBC</p></li><li><p>BACD</p></li><li><p>BADC</p></li></ol>",
    "options": [
      "<p>DBCA</p>",
      "<p>ADBC</p>",
      "<p>BACD</p>",
      "<p>BADC</p>"
    ],
    "answer": "C",
    "type": "MCQ",
    "subject": "English",
    "subtopic": "Para Jumble",
    "year": null,
    "_source": {
      "sourceKind": "bossxcode-web",
      "examBody": "BossXCode",
      "examName": "BossXCode",
      "pageUrl": "https://pt.bossxcode.unaux.com/play#paper-f703404b3f6d37c2",
      "sourceId": "292ca4b035dbcbf1",
      "originalQNum": "9",
      "topic": "Para Jumble",
      "catalogId": "45993ae7db6c903b"
    }
  },
  {
    "uid": "APT-ENG-0492",
    "questionHtml": "<p>Select the most appropriate sequence from the given options to make a meaningful paragraph from jumbled sentences.<br>A. This is because of its aroma, flavour and variety in the market.<br>B. Thus, it leads to poor health and mental disorders among children.<br>C. Children as well as teenagers are tempted towards junk food.<br>D. It has no or negligible nutritional value and high content of sugar and salt.</p>\n<ol style=\"list-style-type:upper-alpha\"><li>BCDA</li><li>ACDB</li><li>CADB</li><li>CDAB</li></ol>",
    "options": [
      "BCDA",
      "ACDB",
      "CADB",
      "CDAB"
    ],
    "answer": "C",
    "type": "MCQ",
    "subject": "English",
    "subtopic": "Para Jumble",
    "year": null,
    "_source": {
      "sourceKind": "bossxcode-web",
      "examBody": "BossXCode",
      "examName": "BossXCode",
      "pageUrl": "https://pt.bossxcode.unaux.com/play#paper-c2c7d18709c609be",
      "sourceId": "2c7f08bfb77ff79d",
      "originalQNum": "10",
      "topic": "Para Jumble",
      "catalogId": "99bb7cfaaa7dc513"
    }
  },
  {
    "uid": "APT-ENG-0493",
    "questionHtml": "<p>Sentences of a paragraph are given below in jumbled order. Arrange the sentences in the correct order to form a meaningful and coherent paragraph. <br>A. But instead of asking the guest to rest, he said, “I have arranged to take you for Shikar.” <br>B. The host welcomed him warmly. <br>C. At last he arrived at the beautiful city. <br>D. Great preparations were made for Amir of Isfahan’s journey to Shiraz.</p>\n<ol style=\"list-style-type:upper-alpha\"><li>CADB</li><li>DCBA</li><li>DCAB</li><li>BDCA</li></ol>",
    "options": [
      "CADB",
      "DCBA",
      "DCAB",
      "BDCA"
    ],
    "answer": "B",
    "type": "MCQ",
    "subject": "English",
    "subtopic": "Para Jumble",
    "year": null,
    "_source": {
      "sourceKind": "bossxcode-web",
      "examBody": "BossXCode",
      "examName": "BossXCode",
      "pageUrl": "https://pt.bossxcode.unaux.com/play#paper-58db70b094c063e3",
      "sourceId": "22808461af462b2c",
      "originalQNum": "10",
      "topic": "Para Jumble",
      "catalogId": "0353496bb1d7b0f0"
    }
  },
  {
    "uid": "APT-ENG-0494",
    "questionHtml": "<p>Sentences of a paragraph are given below in jumbled order. Arrange the sentences in the right order to form a meaningful and coherent paragraph. <br>A. Sculpture and painting form an integral part of temple architecture. <br>B. The city is visited by thousands curious to see the temple in the form of a chariot. <br>C. The finest example of this is Konark Temple in Puri. <br>D. The chariot with immense wheels and horses is carved from stone.</p>\n<ol style=\"list-style-type:upper-alpha\"><li>BCDA</li><li>BCAD</li><li>ABCD</li><li>ACBD</li></ol>",
    "options": [
      "BCDA",
      "BCAD",
      "ABCD",
      "ACBD"
    ],
    "answer": "D",
    "type": "MCQ",
    "subject": "English",
    "subtopic": "Para Jumble",
    "year": null,
    "_source": {
      "sourceKind": "bossxcode-web",
      "examBody": "BossXCode",
      "examName": "BossXCode",
      "pageUrl": "https://pt.bossxcode.unaux.com/play#paper-bbf3f6915c76edfb",
      "sourceId": "8d71cd085e1e897b",
      "originalQNum": "10",
      "topic": "Para Jumble",
      "catalogId": "b7aa877f2b97f6f0"
    }
  },
  {
    "uid": "APT-ENG-0495",
    "questionHtml": "<p>Sentences of a paragraph are given below in jumbled order. Arrange the sentences in the right order to form a meaningful and coherent paragraph. <br>A. There are many secondary reasons as well along with increasing levels of carbon. <br>B. The term is used to describe the unnatural rise in earth’s average temperature. <br>C. Increased carbon dioxide is the primary driver of global warming. <br>D. Global warming is the single biggest threat to life on earth today.</p>\n<ol style=\"list-style-type:upper-alpha\"><li>DABC</li><li>ABCD</li><li>DBCA</li><li>ACBD</li></ol>",
    "options": [
      "DABC",
      "ABCD",
      "DBCA",
      "ACBD"
    ],
    "answer": "C",
    "type": "MCQ",
    "subject": "English",
    "subtopic": "Para Jumble",
    "year": null,
    "_source": {
      "sourceKind": "bossxcode-web",
      "examBody": "BossXCode",
      "examName": "BossXCode",
      "pageUrl": "https://pt.bossxcode.unaux.com/play#paper-f703404b3f6d37c2",
      "sourceId": "cc88b45afce87d3d",
      "originalQNum": "10",
      "topic": "Para Jumble",
      "catalogId": "45993ae7db6c903b"
    }
  },
  {
    "uid": "APT-ENG-0496",
    "questionHtml": "<p>Select the most appropriate sequence from the given options to make a meaningful paragraph from jumbled sentences.<br>A. Upon returning from his travels, he was forced to live in a house where his large family lived.<br>B. Vaikom Muhammad Basheer was a Malayalam fiction writer from Vaikom in Kerela.<br>C. The household was always noisy and full of chaos, no place for a writer surely!<br>D. Apart from family members, myriads of domestic animals also treated the house as their own.</p>\n<ol style=\"list-style-type:upper-alpha\"><li>BCAD</li><li>BCDA</li><li>BADC</li><li>BDCA</li></ol>",
    "options": [
      "BCAD",
      "BCDA",
      "BADC",
      "BDCA"
    ],
    "answer": "C",
    "type": "MCQ",
    "subject": "English",
    "subtopic": "Para Jumble",
    "year": null,
    "_source": {
      "sourceKind": "bossxcode-web",
      "examBody": "BossXCode",
      "examName": "BossXCode",
      "pageUrl": "https://pt.bossxcode.unaux.com/play#paper-c2c7d18709c609be",
      "sourceId": "8b315222a080c527",
      "originalQNum": "11",
      "topic": "Para Jumble",
      "catalogId": "99bb7cfaaa7dc513"
    }
  },
  {
    "uid": "APT-ENG-0497",
    "questionHtml": "<p>Sentences of a paragraph are given below in jumbled order. Arrange the sentences in <br>the correct order to form a meaningful and coherent paragraph. <br>A. It coincided with the 140th birth anniversary of Sardar Vallabhbhai Patel. <br>B. Through this innovative measure, the knowledge of the traditions and culture of <br>different states is being shared. <br>C. The initiative ‘Ek Bharat Shreshtha Bharat’ was launched by the Honourable Prime<br>Minister on 31st October 2015. <br>D. This will lead to an enhanced bonding and national integration.</p>\n<ol style=\"list-style-type:upper-alpha\"><li>CBDA</li><li>ADBC</li><li>ABCD</li><li>CABD</li></ol>",
    "options": [
      "CBDA",
      "ADBC",
      "ABCD",
      "CABD"
    ],
    "answer": "D",
    "type": "MCQ",
    "subject": "English",
    "subtopic": "Para Jumble",
    "year": null,
    "_source": {
      "sourceKind": "bossxcode-web",
      "examBody": "BossXCode",
      "examName": "BossXCode",
      "pageUrl": "https://pt.bossxcode.unaux.com/play#paper-58db70b094c063e3",
      "sourceId": "8533f8cabf403671",
      "originalQNum": "11",
      "topic": "Para Jumble",
      "catalogId": "0353496bb1d7b0f0"
    }
  },
  {
    "uid": "APT-ENG-0498",
    "questionHtml": "<p>Sentences of a paragraph are given below in jumbled order. Arrange the sentences in the right order to form a meaningful and coherent paragraph. <br>A. Information Communication Technology tools have brought in additional changes along with means of communication. <br>B. These changes have enabled man to communicate faster. <br>C. Communication has not only become faster but easier too. <br>D. The result is a more relaxed life than ever before.</p>\n<ol style=\"list-style-type:upper-alpha\"><li><p>ABDC</p></li><li><p>CDBA</p></li><li><p>DBCA</p></li><li><p>ABCD</p></li></ol>",
    "options": [
      "<p>ABDC</p>",
      "<p>CDBA</p>",
      "<p>DBCA</p>",
      "<p>ABCD</p>"
    ],
    "answer": "D",
    "type": "MCQ",
    "subject": "English",
    "subtopic": "Para Jumble",
    "year": null,
    "_source": {
      "sourceKind": "bossxcode-web",
      "examBody": "BossXCode",
      "examName": "BossXCode",
      "pageUrl": "https://pt.bossxcode.unaux.com/play#paper-bbf3f6915c76edfb",
      "sourceId": "8ba8dc754b284283",
      "originalQNum": "11",
      "topic": "Para Jumble",
      "catalogId": "b7aa877f2b97f6f0"
    }
  },
  {
    "uid": "APT-ENG-0499",
    "questionHtml": "<p>Sentences of a paragraph are given below in jumbled order. Arrange the sentences in the right order to form a meaningful and coherent paragraph. <br>A. Whichever soonest made a traveller take off his cloak should be accounted the more powerful. <br>B. They agreed to put the point to test. <br>C. A dispute once arose between the wind and the sun to decide which was the stronger of the two. <br>D. The wind began, and blew with all his might and sent a blast, cold and fierce as a storm.</p>\n<ol style=\"list-style-type:upper-alpha\"><li>CDBA</li><li>ACDB</li><li>CBAD</li><li>BCDA<br></li></ol>",
    "options": [
      "CDBA",
      "ACDB",
      "CBAD",
      "BCDA<br>"
    ],
    "answer": "C",
    "type": "MCQ",
    "subject": "English",
    "subtopic": "Para Jumble",
    "year": null,
    "_source": {
      "sourceKind": "bossxcode-web",
      "examBody": "BossXCode",
      "examName": "BossXCode",
      "pageUrl": "https://pt.bossxcode.unaux.com/play#paper-f703404b3f6d37c2",
      "sourceId": "e220674679cb03f3",
      "originalQNum": "11",
      "topic": "Para Jumble",
      "catalogId": "45993ae7db6c903b"
    }
  },
  {
    "uid": "APT-ENG-0500",
    "questionHtml": "<p>Given below are four sentences which are jumbled. Pick the option that gives their <br>correct order.<br>A. It also wants to know how many students have been provided nutritious food and <br>improved their overall health. <br>B. The Midday Meal Scheme, that aims to provide free food to children, is in focus <br>again. <br>C. About 1.3 million government schools are covered under this welfare program of <br>children. <br>D. The Government now wants to take stock of the implementation of the program,</p>\n<ol style=\"list-style-type:upper-alpha\"><li>BCDA</li><li>ADBC</li><li>BACD</li><li>ADCB</li></ol>",
    "options": [
      "BCDA",
      "ADBC",
      "BACD",
      "ADCB"
    ],
    "answer": "A",
    "type": "MCQ",
    "subject": "English",
    "subtopic": "Para Jumble",
    "year": null,
    "_source": {
      "sourceKind": "bossxcode-web",
      "examBody": "BossXCode",
      "examName": "BossXCode",
      "pageUrl": "https://pt.bossxcode.unaux.com/play#paper-58db70b094c063e3",
      "sourceId": "2561df1fdf62aee4",
      "originalQNum": "12",
      "topic": "Para Jumble",
      "catalogId": "0353496bb1d7b0f0"
    }
  },
  {
    "uid": "APT-ENG-0501",
    "questionHtml": "<p>Select the most appropriate sequence from the given options to make a meaningful paragraph from jumbled sentences.<br>A. Even the most ill-equipped laboratory would have been better than their shed.<br>B. Thus, they did not allow any difficulties to come in their way.<br>C. But their mind was set upon the discovery of radium.<br>D. The curies had to work in extreme poverty.</p>\n<ol style=\"list-style-type:upper-alpha\"><li><p>DACB</p></li><li><p>ABCD</p></li><li><p>ADBC</p></li><li><p>DBCA</p></li></ol>",
    "options": [
      "<p>DACB</p>",
      "<p>ABCD</p>",
      "<p>ADBC</p>",
      "<p>DBCA</p>"
    ],
    "answer": "A",
    "type": "MCQ",
    "subject": "English",
    "subtopic": "Para Jumble",
    "year": null,
    "_source": {
      "sourceKind": "bossxcode-web",
      "examBody": "BossXCode",
      "examName": "BossXCode",
      "pageUrl": "https://pt.bossxcode.unaux.com/play#paper-c2c7d18709c609be",
      "sourceId": "50dabd1b9fcf69fc",
      "originalQNum": "12",
      "topic": "Para Jumble",
      "catalogId": "99bb7cfaaa7dc513"
    }
  },
  {
    "uid": "APT-ENG-0502",
    "questionHtml": "<p>Sentences of a paragraph are given below in jumbled order. Arrange the sentences in the right order to form a meaningful and coherent paragraph. <br>A. I was shocked to find my house unlocked. <br>B. To my astonishment, I found that my son, who had a spare key, had come in my absence. <br>C. Last Sunday I returned home late at night. <br>D. I ran inside in fear that my house has been robbed.</p>\n<ol style=\"list-style-type:upper-alpha\"><li>CDAB</li><li>CADB</li><li>BCDA</li><li>ABCD</li></ol>",
    "options": [
      "CDAB",
      "CADB",
      "BCDA",
      "ABCD"
    ],
    "answer": "B",
    "type": "MCQ",
    "subject": "English",
    "subtopic": "Para Jumble",
    "year": null,
    "_source": {
      "sourceKind": "bossxcode-web",
      "examBody": "BossXCode",
      "examName": "BossXCode",
      "pageUrl": "https://pt.bossxcode.unaux.com/play#paper-f703404b3f6d37c2",
      "sourceId": "fddb2edbe45d29e5",
      "originalQNum": "12",
      "topic": "Para Jumble",
      "catalogId": "45993ae7db6c903b"
    }
  },
  {
    "uid": "APT-ENG-0503",
    "questionHtml": "<p>Sentences of a paragraph are given below in jumbled order. Arrange the sentences in the right order to form a meaningful and coherent paragraph. <br>A. Inspector: “Were you sleeping when the robbers entered the bank?” <br>B. Guard: “The iron grill lock was broken and the bank looked ransacked but the robbers could not take away anything as I had returned quickly.” <br>C. Inspector: “What did you see when you came back?” <br>D. Guard: “No Sir. The bank had closed and I had just gone to relieve myself.”</p>\n<ol style=\"list-style-type:upper-alpha\"><li>BADC</li><li>ABCD</li><li>CDAB</li><li>ADCB</li></ol>",
    "options": [
      "BADC",
      "ABCD",
      "CDAB",
      "ADCB"
    ],
    "answer": "D",
    "type": "MCQ",
    "subject": "English",
    "subtopic": "Para Jumble",
    "year": null,
    "_source": {
      "sourceKind": "bossxcode-web",
      "examBody": "BossXCode",
      "examName": "BossXCode",
      "pageUrl": "https://pt.bossxcode.unaux.com/play#paper-bbf3f6915c76edfb",
      "sourceId": "a4242b0969fd8d4a",
      "originalQNum": "12",
      "topic": "Para Jumble",
      "catalogId": "b7aa877f2b97f6f0"
    }
  },
  {
    "uid": "APT-ENG-0504",
    "questionHtml": "<p>Given below are four jumbled sentences. Select the option that gives their correct order. <br>A. For example, the sound of footsteps followed by the slam of a door are like phrases which convey some information. <br>B. In films, sound effects play the part of words. <br>C. We then know who is performing an action and why, and a clear picture is formed in our mind’s eye. <br>D. Once the sounds are prefaced or followed by a dialogue, the sentence is complete.</p>\n<ol style=\"list-style-type:upper-alpha\"><li>DCBA</li><li>CBDA</li><li>BCDA</li><li>BADC</li></ol>",
    "options": [
      "DCBA",
      "CBDA",
      "BCDA",
      "BADC"
    ],
    "answer": "D",
    "type": "MCQ",
    "subject": "English",
    "subtopic": "Para Jumble",
    "year": null,
    "_source": {
      "sourceKind": "bossxcode-web",
      "examBody": "BossXCode",
      "examName": "BossXCode",
      "pageUrl": "https://pt.bossxcode.unaux.com/play#paper-58db70b094c063e3",
      "sourceId": "a970a888f8076edb",
      "originalQNum": "13",
      "topic": "Para Jumble",
      "catalogId": "0353496bb1d7b0f0"
    }
  },
  {
    "uid": "APT-ENG-0505",
    "questionHtml": "<p>Select the most appropriate sequence from the given options to make a meaningful paragraph from jumbled sentences.<br>A. Aesop was one of them who lived in Greece about 2500 years ago.<br>B. He told many interesting stories to the people.<br>C. There were many talented people in ancient Greece.<br>D. Although, he was very ugly, he had a very clever brain.</p>\n<ol style=\"list-style-type:upper-alpha\"><li>BDAC</li><li>CADB</li><li>CDBA</li><li>BADC</li></ol>",
    "options": [
      "BDAC",
      "CADB",
      "CDBA",
      "BADC"
    ],
    "answer": "B",
    "type": "MCQ",
    "subject": "English",
    "subtopic": "Para Jumble",
    "year": null,
    "_source": {
      "sourceKind": "bossxcode-web",
      "examBody": "BossXCode",
      "examName": "BossXCode",
      "pageUrl": "https://pt.bossxcode.unaux.com/play#paper-c2c7d18709c609be",
      "sourceId": "4d3c9ea0888df771",
      "originalQNum": "13",
      "topic": "Para Jumble",
      "catalogId": "99bb7cfaaa7dc513"
    }
  },
  {
    "uid": "APT-ENG-0506",
    "questionHtml": "<p>Sentences of a paragraph are given below in jumbled order. Arrange the sentences in the right order to form a meaningful and coherent paragraph. <br>A. A fox, hearing the cock and thinking to make a meal of him, came and stood under the tree. <br>B. As the night passed away and the day dawned, the cock, according to his custom, set up a shrill crowing. <br>C. A dog and a cock having struck up an acquaintance, went out on their travels together. <br>D. Nightfall found them in a forest, so the cock, flying up on a tree, perched among the branches, while the dog dozed below at the foot.</p>\n<ol style=\"list-style-type:upper-alpha\"><li><p>DCAB</p></li><li><p>CDBA</p></li><li><p>BCDA</p></li><li><p>CABD</p></li></ol>",
    "options": [
      "<p>DCAB</p>",
      "<p>CDBA</p>",
      "<p>BCDA</p>",
      "<p>CABD</p>"
    ],
    "answer": "B",
    "type": "MCQ",
    "subject": "English",
    "subtopic": "Para Jumble",
    "year": null,
    "_source": {
      "sourceKind": "bossxcode-web",
      "examBody": "BossXCode",
      "examName": "BossXCode",
      "pageUrl": "https://pt.bossxcode.unaux.com/play#paper-bbf3f6915c76edfb",
      "sourceId": "16a119a1872110d4",
      "originalQNum": "13",
      "topic": "Para Jumble",
      "catalogId": "b7aa877f2b97f6f0"
    }
  },
  {
    "uid": "APT-ENG-0507",
    "questionHtml": "<p>Sentences of a paragraph are given below in jumbled order. Arrange the sentences in the right order to form a meaningful and coherent paragraph. <br>A. But in snapping at the supposed treasure, he dropped the bit he was carrying, and so lost all. <br>B. When he was crossing a river on his way home, he saw his own shadow reflected in the stream below.  <br>C. Thinking that it was another dog with another piece of meat, he resolved to make himself master of that also. <br>D. A dog had stolen a piece of meat out of a butcher's shop.</p>\n<ol style=\"list-style-type:upper-alpha\"><li>DACB</li><li>BDCA</li><li>ACDB</li><li>DBCA</li></ol>",
    "options": [
      "DACB",
      "BDCA",
      "ACDB",
      "DBCA"
    ],
    "answer": "D",
    "type": "MCQ",
    "subject": "English",
    "subtopic": "Para Jumble",
    "year": null,
    "_source": {
      "sourceKind": "bossxcode-web",
      "examBody": "BossXCode",
      "examName": "BossXCode",
      "pageUrl": "https://pt.bossxcode.unaux.com/play#paper-f703404b3f6d37c2",
      "sourceId": "9e5324cdb63bf1b4",
      "originalQNum": "13",
      "topic": "Para Jumble",
      "catalogId": "45993ae7db6c903b"
    }
  },
  {
    "uid": "APT-ENG-0508",
    "questionHtml": "<p>Select the most appropriate sequence from the given options to make a meaningful paragraph from jumbled sentences.<br>A. He is a gifted volleyball player.<br>B. But now a days he does not play international matches.<br>C. It is because he had an accident last year.<br>D. Sanjay is my best friend.</p>\n<ol style=\"list-style-type:upper-alpha\"><li>DABC</li><li>DCAB</li><li>CDBA</li><li>ABCD</li></ol>",
    "options": [
      "DABC",
      "DCAB",
      "CDBA",
      "ABCD"
    ],
    "answer": "A",
    "type": "MCQ",
    "subject": "English",
    "subtopic": "Para Jumble",
    "year": null,
    "_source": {
      "sourceKind": "bossxcode-web",
      "examBody": "BossXCode",
      "examName": "BossXCode",
      "pageUrl": "https://pt.bossxcode.unaux.com/play#paper-c2c7d18709c609be",
      "sourceId": "78e756cbb007b991",
      "originalQNum": "14",
      "topic": "Para Jumble",
      "catalogId": "99bb7cfaaa7dc513"
    }
  },
  {
    "uid": "APT-ENG-0509",
    "questionHtml": "<p>Sentences of a paragraph are given below in jumbled order. Arrange the sentences in the correct order to form a meaningful and coherent paragraph. <br>A. They always shared machinery and goods as needed without a hitch. <br>B. Then they had the first serious quarrel in 40 years of farming side by side.<br>C. And unfortunately, the long collaboration fell apart. <br>D. Two brothers lived on adjoining farms in a small village</p>\n<ol style=\"list-style-type:upper-alpha\"><li>DBCA</li><li>DABC</li><li>CADB</li><li>BCAD</li></ol>",
    "options": [
      "DBCA",
      "DABC",
      "CADB",
      "BCAD"
    ],
    "answer": "B",
    "type": "MCQ",
    "subject": "English",
    "subtopic": "Para Jumble",
    "year": null,
    "_source": {
      "sourceKind": "bossxcode-web",
      "examBody": "BossXCode",
      "examName": "BossXCode",
      "pageUrl": "https://pt.bossxcode.unaux.com/play#paper-58db70b094c063e3",
      "sourceId": "5da202dcb82fa68d",
      "originalQNum": "14",
      "topic": "Para Jumble",
      "catalogId": "0353496bb1d7b0f0"
    }
  },
  {
    "uid": "APT-ENG-0510",
    "questionHtml": "<p>Sentences of a paragraph are given below in jumbled order. Arrange the sentences in the right order to form a meaningful and coherent paragraph. <br>A. Most important, however, are its oils, which are extracted, processed, and marketed for culinary, medicinal, and cosmetic uses alike. <br>B. Coconut products are used to make everything from clothing to animal feed to beauty creams. <br>C. The coconut is a very useful plant with a wide range of products being sourced from it. <br>D. Its kernel is harvested for its edible flesh and delicious water, while its husk is used for its strong fibres.</p>\n<ol style=\"list-style-type:upper-alpha\"><li><p>CBDA</p></li><li><p>ADBC</p></li><li><p>BCAD</p></li><li><p>CADB</p></li></ol>",
    "options": [
      "<p>CBDA</p>",
      "<p>ADBC</p>",
      "<p>BCAD</p>",
      "<p>CADB</p>"
    ],
    "answer": "A",
    "type": "MCQ",
    "subject": "English",
    "subtopic": "Para Jumble",
    "year": null,
    "_source": {
      "sourceKind": "bossxcode-web",
      "examBody": "BossXCode",
      "examName": "BossXCode",
      "pageUrl": "https://pt.bossxcode.unaux.com/play#paper-f703404b3f6d37c2",
      "sourceId": "23fc598aa9899aa8",
      "originalQNum": "14",
      "topic": "Para Jumble",
      "catalogId": "45993ae7db6c903b"
    }
  },
  {
    "uid": "APT-ENG-0511",
    "questionHtml": "<p>Sentences of a paragraph are given below in jumbled order. Arrange the sentences in the right order to form a meaningful and coherent paragraph. <br>A. Though they had never ever heard Subha utter their names, they unfailingly recognized her footsteps as she came into their shed.  <br>B. They even understood the precious moments between them as she loved and cuddled them, scolded them, and pleaded to them. <br>C. Subha did really have a close circle of friends and companions; they were Sarbasi and Panguli, the two cows living in their cow-shed. <br>D. They understood the silent, melancholy tune of her unspoken words during those moments, and the intensity of her expressions more easily than the spoken language of other humans.</p>\n<ol style=\"list-style-type:upper-alpha\"><li>ADBC</li><li>DABC</li><li>CADB</li><li>CBDA</li></ol>",
    "options": [
      "ADBC",
      "DABC",
      "CADB",
      "CBDA"
    ],
    "answer": "C",
    "type": "MCQ",
    "subject": "English",
    "subtopic": "Para Jumble",
    "year": null,
    "_source": {
      "sourceKind": "bossxcode-web",
      "examBody": "BossXCode",
      "examName": "BossXCode",
      "pageUrl": "https://pt.bossxcode.unaux.com/play#paper-bbf3f6915c76edfb",
      "sourceId": "ebe33f9c05fa6610",
      "originalQNum": "14",
      "topic": "Para Jumble",
      "catalogId": "b7aa877f2b97f6f0"
    }
  },
  {
    "uid": "APT-ENG-0512",
    "questionHtml": "<p>Given below are four sentences which are jumbled. Pick the option that gives their correct order. <br>A. The sectors included agriculture, public health and public utilities among others. <br>B. The GGI framework covered 10 sectors and 58 Industries.<br>C. The Good Governance Index (GGI) 2021scores have been declared. <br>D. The objective was to provide quantifiable data to compare the performance of different States and Union Territories in these sectors.</p>\n<ol style=\"list-style-type:upper-alpha\"><li><p>CADB</p></li><li><p>CBAD</p></li><li><p>ABDC</p></li><li><p>BACD</p></li></ol>",
    "options": [
      "<p>CADB</p>",
      "<p>CBAD</p>",
      "<p>ABDC</p>",
      "<p>BACD</p>"
    ],
    "answer": "B",
    "type": "MCQ",
    "subject": "English",
    "subtopic": "Para Jumble",
    "year": null,
    "_source": {
      "sourceKind": "bossxcode-web",
      "examBody": "BossXCode",
      "examName": "BossXCode",
      "pageUrl": "https://pt.bossxcode.unaux.com/play#paper-58db70b094c063e3",
      "sourceId": "85b9da0dfb87ba80",
      "originalQNum": "15",
      "topic": "Para Jumble",
      "catalogId": "0353496bb1d7b0f0"
    }
  },
  {
    "uid": "APT-ENG-0513",
    "questionHtml": "<p>Select the most appropriate sequence from the given options to make a meaningful paragraph from jumbled sentences.<br>A. Although I had a fear of water, I thought it was an important skill I should learn.<br>B. However, what I didn't realize was that it would also make me a more confident person.<br>C. I also thought it would be a good exercise that would make me physically stronger.<br>D. One of the hardest things I've had to do was to learn how to swim.</p>\n<ol style=\"list-style-type:upper-alpha\"><li><p>ACDB</p></li><li><p>DCBA</p></li><li><p>DACB</p></li><li><p>BADC</p></li></ol>",
    "options": [
      "<p>ACDB</p>",
      "<p>DCBA</p>",
      "<p>DACB</p>",
      "<p>BADC</p>"
    ],
    "answer": "C",
    "type": "MCQ",
    "subject": "English",
    "subtopic": "Para Jumble",
    "year": null,
    "_source": {
      "sourceKind": "bossxcode-web",
      "examBody": "BossXCode",
      "examName": "BossXCode",
      "pageUrl": "https://pt.bossxcode.unaux.com/play#paper-c2c7d18709c609be",
      "sourceId": "47ebaf19808b815f",
      "originalQNum": "15",
      "topic": "Para Jumble",
      "catalogId": "99bb7cfaaa7dc513"
    }
  },
  {
    "uid": "APT-ENG-0514",
    "questionHtml": "<p>Sentences of a paragraph are given below in jumbled order. Arrange the sentences in the right order to form a meaningful and coherent paragraph. <br>A. It is essential for the marketer to study the behaviour of the consumers in order to make better strategic marketing decisions. <br>B. The study of consumer behaviour is equally important for the non-profit organisations such as governmental agencies, hospitals, NGOs, charitable organisations. <br>C. Thus, by studying the consumer behaviour before and during purchase helps in production scheduling, designing, pricing, positioning, segmentation, advertising and other promotional activities. <br>D. If the marketer has complete knowledge about the consumer’s likings or disliking, then he can predict the response of the potential customers towards his offerings.</p>\n<ol style=\"list-style-type:upper-alpha\"><li><p>ADCB</p></li><li><p>BCAD</p></li><li><p>CDBA</p></li><li><p>ACBD</p></li></ol>",
    "options": [
      "<p>ADCB</p>",
      "<p>BCAD</p>",
      "<p>CDBA</p>",
      "<p>ACBD</p>"
    ],
    "answer": "A",
    "type": "MCQ",
    "subject": "English",
    "subtopic": "Para Jumble",
    "year": null,
    "_source": {
      "sourceKind": "bossxcode-web",
      "examBody": "BossXCode",
      "examName": "BossXCode",
      "pageUrl": "https://pt.bossxcode.unaux.com/play#paper-bbf3f6915c76edfb",
      "sourceId": "246c8c05e75a77d0",
      "originalQNum": "15",
      "topic": "Para Jumble",
      "catalogId": "b7aa877f2b97f6f0"
    }
  },
  {
    "uid": "APT-ENG-0515",
    "questionHtml": "<p>Sentences of a paragraph are given below in jumbled order. Arrange the sentences in the right order to form a meaningful and coherent paragraph. <br>A. These kinds of sharks are known as obligate ram ventilators because they draw water in through their mouths and force it out through their gills. <br>B. They use a method called buccal pumping, in which water is pulled in through the mouth and forced out through the gills by the cheek muscles. <br>C. It is true that many types of sharks must keep moving in order to receive life-giving oxygen from the water passing through their gills. <br>D. Other types of sharks are able to remain stationary because they possess special structures called  spiracles, which force water out through their gills.</p>\n<ol style=\"list-style-type:upper-alpha\"><li>DABC</li><li>CDAB</li><li>BCDA</li><li>CABD</li></ol>",
    "options": [
      "DABC",
      "CDAB",
      "BCDA",
      "CABD"
    ],
    "answer": "D",
    "type": "MCQ",
    "subject": "English",
    "subtopic": "Para Jumble",
    "year": null,
    "_source": {
      "sourceKind": "bossxcode-web",
      "examBody": "BossXCode",
      "examName": "BossXCode",
      "pageUrl": "https://pt.bossxcode.unaux.com/play#paper-f703404b3f6d37c2",
      "sourceId": "1e448077c971c721",
      "originalQNum": "15",
      "topic": "Para Jumble",
      "catalogId": "45993ae7db6c903b"
    }
  },
  {
    "uid": "APT-ENG-0516",
    "questionHtml": "<p>Arrange the statements in the correct order to make a meaningful paragraph. <br>A. Impressed with Jane’s patience with animals, he chose her for the mission to understand chimpanzees. <br>B. In 1957, she went to Kenya where she met the British paleoanthropologist, Louis Leakey. <br>C. As a child she would wait for hours to observe a chicken laying an egg. <br>D. Jane Goodall grew up in the English town of Bournemouth.</p>\n<ol style=\"list-style-type:upper-alpha\"><li>DCBA</li><li>DBAC</li><li>CDBA</li><li>ABCD</li></ol>",
    "options": [
      "DCBA",
      "DBAC",
      "CDBA",
      "ABCD"
    ],
    "answer": "A",
    "type": "MCQ",
    "subject": "English",
    "subtopic": "Para Jumble",
    "year": null,
    "_source": {
      "sourceKind": "bossxcode-web",
      "examBody": "BossXCode",
      "examName": "BossXCode",
      "pageUrl": "https://pt.bossxcode.unaux.com/play#paper-58db70b094c063e3",
      "sourceId": "d2008fadd3551c9e",
      "originalQNum": "16",
      "topic": "Para Jumble",
      "catalogId": "0353496bb1d7b0f0"
    }
  },
  {
    "uid": "APT-ENG-0517",
    "questionHtml": "<p>Select the most appropriate sequence from the given options to make a meaningful paragraph from jumbled sentences.<br>A. During the celebration, many people display a set of ornamental dolls known as 'Hina' dolls.<br>B. Hinamatsuri is a celebration of the girls in Japan wishing them a bright future.<br>C. These royal-looking dolls are dressed in the clothing of the Heian period.<br>D. These dolls represent the Emperor, Empress and royal representatives.</p>\n<ol style=\"list-style-type:upper-alpha\"><li>ACBD</li><li>CDBA</li><li>DBAC</li><li>BADC</li></ol>",
    "options": [
      "ACBD",
      "CDBA",
      "DBAC",
      "BADC"
    ],
    "answer": "D",
    "type": "MCQ",
    "subject": "English",
    "subtopic": "Para Jumble",
    "year": null,
    "_source": {
      "sourceKind": "bossxcode-web",
      "examBody": "BossXCode",
      "examName": "BossXCode",
      "pageUrl": "https://pt.bossxcode.unaux.com/play#paper-c2c7d18709c609be",
      "sourceId": "bae0637bf6770471",
      "originalQNum": "16",
      "topic": "Para Jumble",
      "catalogId": "99bb7cfaaa7dc513"
    }
  },
  {
    "uid": "APT-ENG-0518",
    "questionHtml": "<p>Sentences of a paragraph are given below in jumbled order. Arrange the sentences in the right order to form a meaningful and coherent paragraph. <br>A. An old mouse, who was wise enough to keep his distance, whispered to a friend, “Many a bag have I seen in my day, but never one with a cat's head”. <br>B. She hoped that the mice would no longer be afraid to come near her. <br>C. A cat, grown feeble with age and no longer able to hunt mice as she once did, thought to herself how she might entice them within reach of her paw.<br>D. Thinking that she might pass herself off for a bag or for a dead cat at least, she suspended herself by the hind legs from a peg.</p>\n<ol style=\"list-style-type:upper-alpha\"><li>CADB</li><li>DCBA</li><li>ABDC</li><li>CDBA</li></ol>",
    "options": [
      "CADB",
      "DCBA",
      "ABDC",
      "CDBA"
    ],
    "answer": "D",
    "type": "MCQ",
    "subject": "English",
    "subtopic": "Para Jumble",
    "year": null,
    "_source": {
      "sourceKind": "bossxcode-web",
      "examBody": "BossXCode",
      "examName": "BossXCode",
      "pageUrl": "https://pt.bossxcode.unaux.com/play#paper-f703404b3f6d37c2",
      "sourceId": "54a334328338fee4",
      "originalQNum": "16",
      "topic": "Para Jumble",
      "catalogId": "45993ae7db6c903b"
    }
  },
  {
    "uid": "APT-ENG-0519",
    "questionHtml": "<p>Sentences of a paragraph are given below in jumbled order. Arrange the sentences in the right order to form a meaningful and coherent paragraph. <br>A. The mouse, however, reached his hole in safety. <br>B. A bull was bitten by a mouse, and, pained by the wound, tried to capture him. <br>C. The mouse, peeping out, crept up his flank and, again biting him, retreated to his hole. <br>D. The bull dug into the walls with his horns until, wearied, he crouched down and slept by the hole.</p>\n<ol style=\"list-style-type:upper-alpha\"><li><p>DACB</p></li><li><p>BADC</p></li><li><p>BCDA</p></li><li><p>ADBC</p></li></ol>",
    "options": [
      "<p>DACB</p>",
      "<p>BADC</p>",
      "<p>BCDA</p>",
      "<p>ADBC</p>"
    ],
    "answer": "B",
    "type": "MCQ",
    "subject": "English",
    "subtopic": "Para Jumble",
    "year": null,
    "_source": {
      "sourceKind": "bossxcode-web",
      "examBody": "BossXCode",
      "examName": "BossXCode",
      "pageUrl": "https://pt.bossxcode.unaux.com/play#paper-bbf3f6915c76edfb",
      "sourceId": "07394386a2091687",
      "originalQNum": "16",
      "topic": "Para Jumble",
      "catalogId": "b7aa877f2b97f6f0"
    }
  },
  {
    "uid": "APT-ENG-0520",
    "questionHtml": "<p>Select the most appropriate sequence from the given options to make a meaningful paragraph from jumbled sentences.<br>A. There are many gadgets that are operated by a remote control and contain a silicon chip.<br>B. This produces an infra-red beam, made up of electromagnetic waves.<br>C. When a button is pressed on the remote control, the chip sets off an electromagnetic vibration.<br>D. The beam carries a coded signal for operating the systems.</p>\n<ol style=\"list-style-type:upper-alpha\"><li>ADCB</li><li>ACDB</li><li>ACBD</li><li>BACD</li></ol>",
    "options": [
      "ADCB",
      "ACDB",
      "ACBD",
      "BACD"
    ],
    "answer": "C",
    "type": "MCQ",
    "subject": "English",
    "subtopic": "Para Jumble",
    "year": null,
    "_source": {
      "sourceKind": "bossxcode-web",
      "examBody": "BossXCode",
      "examName": "BossXCode",
      "pageUrl": "https://pt.bossxcode.unaux.com/play#paper-c2c7d18709c609be",
      "sourceId": "b06dd8fdc4a7b657",
      "originalQNum": "17",
      "topic": "Para Jumble",
      "catalogId": "99bb7cfaaa7dc513"
    }
  },
  {
    "uid": "APT-ENG-0521",
    "questionHtml": "<p>Sentences of a paragraph are given below in jumbled order. Arrange the sentences in the correct order to form a meaningful and coherent paragraph. <br>A. Thus, shared laughter is one of the most effective tools in maintaining healthy relationships. <br>B. Emotional sharing builds strong and lasting bonds. <br>C. It also helps in healing resentments and hurt. <br>D. But sharing laughter brings joy and freshness to relationships.</p>\n<ol style=\"list-style-type:upper-alpha\"><li>BCAD</li><li>DCBA</li><li>DCAB</li><li>BDCA</li></ol>",
    "options": [
      "BCAD",
      "DCBA",
      "DCAB",
      "BDCA"
    ],
    "answer": "D",
    "type": "MCQ",
    "subject": "English",
    "subtopic": "Para Jumble",
    "year": null,
    "_source": {
      "sourceKind": "bossxcode-web",
      "examBody": "BossXCode",
      "examName": "BossXCode",
      "pageUrl": "https://pt.bossxcode.unaux.com/play#paper-58db70b094c063e3",
      "sourceId": "66e7732895562644",
      "originalQNum": "17",
      "topic": "Para Jumble",
      "catalogId": "0353496bb1d7b0f0"
    }
  },
  {
    "uid": "APT-ENG-0522",
    "questionHtml": "<p>Sentences of a paragraph are given below in jumbled order. Arrange the sentences in the right order to form a meaningful and coherent paragraph. <br>A. In some cases, the problem of the lowering of the river bottom has caused the water table of the surrounding area to drop, which has adversely affected agriculture. <br>B. Also, another problem, canalization with its extensive system of locks and navigation dams, often seriously disrupts riverine ecosystems. <br>C. The ever-increasing exploitation of rivers has given rise to a variety of problems.  <br>D. Further, extensive commercial navigation of rivers has resulted in much artificial improvement of natural channels, including increasing the depth of the channels to permit passage of larger vessels.</p>\n<ol style=\"list-style-type:upper-alpha\"><li>BDAC</li><li>DCAB</li><li>CABD</li><li>CDAB</li></ol>",
    "options": [
      "BDAC",
      "DCAB",
      "CABD",
      "CDAB"
    ],
    "answer": "C",
    "type": "MCQ",
    "subject": "English",
    "subtopic": "Para Jumble",
    "year": null,
    "_source": {
      "sourceKind": "bossxcode-web",
      "examBody": "BossXCode",
      "examName": "BossXCode",
      "pageUrl": "https://pt.bossxcode.unaux.com/play#paper-f703404b3f6d37c2",
      "sourceId": "85229f3a7f9286bb",
      "originalQNum": "17",
      "topic": "Para Jumble",
      "catalogId": "45993ae7db6c903b"
    }
  },
  {
    "uid": "APT-ENG-0523",
    "questionHtml": "<p>Sentences of a paragraph are given below in jumbled order. Arrange the sentences in the right order to form a meaningful and coherent paragraph. <br>A. It is also a rich source of news updates around the world.  <br>B. Older people and children remain glued to it. <br>C. It has become a great source of entertainment for all. <br>D. TV has become a powerful medium these days.</p>\n<ol style=\"list-style-type:upper-alpha\"><li>DBCA</li><li>BDCA</li><li>ACBD</li><li>ABCD</li></ol>",
    "options": [
      "DBCA",
      "BDCA",
      "ACBD",
      "ABCD"
    ],
    "answer": "A",
    "type": "MCQ",
    "subject": "English",
    "subtopic": "Para Jumble",
    "year": null,
    "_source": {
      "sourceKind": "bossxcode-web",
      "examBody": "BossXCode",
      "examName": "BossXCode",
      "pageUrl": "https://pt.bossxcode.unaux.com/play#paper-bbf3f6915c76edfb",
      "sourceId": "51b3e48ea81c402b",
      "originalQNum": "17",
      "topic": "Para Jumble",
      "catalogId": "b7aa877f2b97f6f0"
    }
  },
  {
    "uid": "APT-ENG-0524",
    "questionHtml": "<p>Select the most appropriate sequence from the given options to make a meaningful paragraph from jumbled sentences.<br>A. It is called the atmosphere.<br>B. All parts of the earth are surrounded by air.<br>C. Livings beings breathe in and breathe out the air all the time.<br>D. This process is called respiration.</p>\n<ol style=\"list-style-type:upper-alpha\"><li>CBAD</li><li>ACDB</li><li>BACD</li><li>DACB</li></ol>",
    "options": [
      "CBAD",
      "ACDB",
      "BACD",
      "DACB"
    ],
    "answer": "C",
    "type": "MCQ",
    "subject": "English",
    "subtopic": "Para Jumble",
    "year": null,
    "_source": {
      "sourceKind": "bossxcode-web",
      "examBody": "BossXCode",
      "examName": "BossXCode",
      "pageUrl": "https://pt.bossxcode.unaux.com/play#paper-c2c7d18709c609be",
      "sourceId": "bd395c49aec2e311",
      "originalQNum": "18",
      "topic": "Para Jumble",
      "catalogId": "99bb7cfaaa7dc513"
    }
  },
  {
    "uid": "APT-ENG-0525",
    "questionHtml": "<p>Sentences of a paragraph are given below in jumbled order. Arrange the sentences in the correct order to form a meaningful and coherent paragraph. <br>A. The British were exploiting the indigo farmers in the area. <br>B. He lived in the district until the exploitation of the farmers was successfully <br>stopped. <br>C. Gandhiji’s Satyagraha for India’s Independence began with the famous ‘Champaran movement’ in Bihar. <br>D. So, Gandhiji visited Motihari, the district headquarters of Champaran, in 1917 to protest against the British.</p>\n<ol style=\"list-style-type:upper-alpha\"><li>ADBC</li><li>CABD</li><li>ACBD</li><li>CADB</li></ol>",
    "options": [
      "ADBC",
      "CABD",
      "ACBD",
      "CADB"
    ],
    "answer": "D",
    "type": "MCQ",
    "subject": "English",
    "subtopic": "Para Jumble",
    "year": null,
    "_source": {
      "sourceKind": "bossxcode-web",
      "examBody": "BossXCode",
      "examName": "BossXCode",
      "pageUrl": "https://pt.bossxcode.unaux.com/play#paper-58db70b094c063e3",
      "sourceId": "68d705ed360e0f11",
      "originalQNum": "18",
      "topic": "Para Jumble",
      "catalogId": "0353496bb1d7b0f0"
    }
  },
  {
    "uid": "APT-ENG-0526",
    "questionHtml": "<p>Sentences of a paragraph are given below in jumbled order. Arrange the sentences in the right order to form a meaningful and coherent paragraph. <br>A. He was caught by the police on the spot. <br>B. Anil bought a car last week. <br>C. Unfortunately, the car met with an accident today. <br>D. The accident took place due to the carelessness of his driver.</p>\n<ol style=\"list-style-type:upper-alpha\"><li>CDBA</li><li>ABDC</li><li>BACD</li><li>BCDA</li></ol>",
    "options": [
      "CDBA",
      "ABDC",
      "BACD",
      "BCDA"
    ],
    "answer": "D",
    "type": "MCQ",
    "subject": "English",
    "subtopic": "Para Jumble",
    "year": null,
    "_source": {
      "sourceKind": "bossxcode-web",
      "examBody": "BossXCode",
      "examName": "BossXCode",
      "pageUrl": "https://pt.bossxcode.unaux.com/play#paper-f703404b3f6d37c2",
      "sourceId": "ec5ad1f88a4aa038",
      "originalQNum": "18",
      "topic": "Para Jumble",
      "catalogId": "45993ae7db6c903b"
    }
  },
  {
    "uid": "APT-ENG-0527",
    "questionHtml": "<p>Sentences of a paragraph are given below in jumbled order. Arrange the sentences in the right order to form a meaningful and coherent paragraph. <br>A. “Buy sweet apples, or none at all”, he instructed his servant. <br>B. A rich man sent his servant to an orchard to buy some apples. <br>C. The servant asked, “How am I to know that all of them are sweet if I taste just one?” <br>D. The owner of the orchard said to the servant, “All my apples are sweet. Try one.”</p>\n<ol style=\"list-style-type:upper-alpha\"><li><p>ABCD</p></li><li><p>BDAC</p></li><li><p>BADC</p></li><li><p>ACBD</p></li></ol>",
    "options": [
      "<p>ABCD</p>",
      "<p>BDAC</p>",
      "<p>BADC</p>",
      "<p>ACBD</p>"
    ],
    "answer": "C",
    "type": "MCQ",
    "subject": "English",
    "subtopic": "Para Jumble",
    "year": null,
    "_source": {
      "sourceKind": "bossxcode-web",
      "examBody": "BossXCode",
      "examName": "BossXCode",
      "pageUrl": "https://pt.bossxcode.unaux.com/play#paper-bbf3f6915c76edfb",
      "sourceId": "b9271940a5d93fad",
      "originalQNum": "18",
      "topic": "Para Jumble",
      "catalogId": "b7aa877f2b97f6f0"
    }
  },
  {
    "uid": "APT-ENG-0528",
    "questionHtml": "<p>Given below are four jumbled sentences. Select the option that gives their correct order. <br>A. Expert mechanics labored over the plane for three hours. <br>B. A small nut had fallen into a channel which prevented the gear from moving. <br>C. A huge plane was forced to crash land when its landing gear got stuck. <br>D. They were amazed when they discovered what had caused the mechanical failure.</p>\n<ol style=\"list-style-type:upper-alpha\"><li>DBAC</li><li>BADC</li><li>ACBD</li><li>CADB</li></ol>",
    "options": [
      "DBAC",
      "BADC",
      "ACBD",
      "CADB"
    ],
    "answer": "D",
    "type": "MCQ",
    "subject": "English",
    "subtopic": "Para Jumble",
    "year": null,
    "_source": {
      "sourceKind": "bossxcode-web",
      "examBody": "BossXCode",
      "examName": "BossXCode",
      "pageUrl": "https://pt.bossxcode.unaux.com/play#paper-58db70b094c063e3",
      "sourceId": "da31ec04c5b2980e",
      "originalQNum": "19",
      "topic": "Para Jumble",
      "catalogId": "0353496bb1d7b0f0"
    }
  },
  {
    "uid": "APT-ENG-0529",
    "questionHtml": "<p>Sentences of a paragraph are given below in jumbled order. Arrange the sentences in the right order to form a meaningful and coherent paragraph. <br>A. But a dove that happened to be sitting on a neighbouring tree saw the ant’s danger and, plucking off a leaf, let it drop into the water before him. <br>B. Just at that time, a fowler was spreading his net and was in the act of ensnaring the dove, when the ant, perceiving his object, bit his heel. <br>C. An ant went to a fountain to quench his thirst and, tumbling in, almost drowned. <br>D. The ant mounting upon it, was presently wafted safely ashore.</p>\n<ol style=\"list-style-type:upper-alpha\"><li>ABCD</li><li>CBAD</li><li>CADB</li><li>DCAB</li></ol>",
    "options": [
      "ABCD",
      "CBAD",
      "CADB",
      "DCAB"
    ],
    "answer": "C",
    "type": "MCQ",
    "subject": "English",
    "subtopic": "Para Jumble",
    "year": null,
    "_source": {
      "sourceKind": "bossxcode-web",
      "examBody": "BossXCode",
      "examName": "BossXCode",
      "pageUrl": "https://pt.bossxcode.unaux.com/play#paper-f703404b3f6d37c2",
      "sourceId": "4e8808b5601b51ba",
      "originalQNum": "19",
      "topic": "Para Jumble",
      "catalogId": "45993ae7db6c903b"
    }
  },
  {
    "uid": "APT-ENG-0530",
    "questionHtml": "<p>Sentences of a paragraph are given below in jumbled order. Arrange the sentences in the right order to form a meaningful and coherent paragraph. <br>A. Ram introduced Shyam to everyone and then served snacks to them. <br>B. After he cut the cake, all of them danced for a long time. <br>C. When Shyam reached his house, his classmates had already arrived. <br>D. Ram invited his friend Shyam on his birthday.</p>\n<ol style=\"list-style-type:upper-alpha\"><li><p>DBAC</p></li><li><p>ABCD</p></li><li><p>ACDB</p></li><li><p>DCAB</p></li></ol>",
    "options": [
      "<p>DBAC</p>",
      "<p>ABCD</p>",
      "<p>ACDB</p>",
      "<p>DCAB</p>"
    ],
    "answer": "D",
    "type": "MCQ",
    "subject": "English",
    "subtopic": "Para Jumble",
    "year": null,
    "_source": {
      "sourceKind": "bossxcode-web",
      "examBody": "BossXCode",
      "examName": "BossXCode",
      "pageUrl": "https://pt.bossxcode.unaux.com/play#paper-bbf3f6915c76edfb",
      "sourceId": "4de9f3f0fcfc3528",
      "originalQNum": "19",
      "topic": "Para Jumble",
      "catalogId": "b7aa877f2b97f6f0"
    }
  },
  {
    "uid": "APT-ENG-0531",
    "questionHtml": "<p>Sentences of a paragraph are given below in jumbled order. Arrange the sentences in the right order to form a meaningful and coherent paragraph. <br>A. However, its importance is primarily for its location. <br>B. But unlike other rivers, it is not used for shipping. <br>C. Although not the longest river, the Rio Grande is the most important river in America.  <br>D. America has several long river systems.</p>\n<ol style=\"list-style-type:upper-alpha\"><li>DABC</li><li>DCBA</li><li>ABCD</li><li>DCAB</li></ol>",
    "options": [
      "DABC",
      "DCBA",
      "ABCD",
      "DCAB"
    ],
    "answer": "B",
    "type": "MCQ",
    "subject": "English",
    "subtopic": "Para Jumble",
    "year": null,
    "_source": {
      "sourceKind": "bossxcode-web",
      "examBody": "BossXCode",
      "examName": "BossXCode",
      "pageUrl": "https://pt.bossxcode.unaux.com/play#paper-f703404b3f6d37c2",
      "sourceId": "72697da21aa77f84",
      "originalQNum": "20",
      "topic": "Para Jumble",
      "catalogId": "45993ae7db6c903b"
    }
  },
  {
    "uid": "APT-ENG-0532",
    "questionHtml": "<p>Sentences of a paragraph are given below in jumbled order. Arrange the sentences in the right order to form a meaningful and coherent paragraph. <br>A. Shopkeeper: “Not at all. It is hardly a two-minute walk from here.” <br>B. Boy: “Can you please show me the way to the post office?” <br>C. Shopkeeper: “Go straight from here and take a right turn.” <br>D. Boy: “Is it very far off from here?”</p>\n<ol style=\"list-style-type:upper-alpha\"><li><p>CDAB</p></li><li><p>DCBA</p></li><li><p>BCDA</p></li><li><p>BADC</p></li></ol>",
    "options": [
      "<p>CDAB</p>",
      "<p>DCBA</p>",
      "<p>BCDA</p>",
      "<p>BADC</p>"
    ],
    "answer": "C",
    "type": "MCQ",
    "subject": "English",
    "subtopic": "Para Jumble",
    "year": null,
    "_source": {
      "sourceKind": "bossxcode-web",
      "examBody": "BossXCode",
      "examName": "BossXCode",
      "pageUrl": "https://pt.bossxcode.unaux.com/play#paper-bbf3f6915c76edfb",
      "sourceId": "a9ad41288fbf1875",
      "originalQNum": "20",
      "topic": "Para Jumble",
      "catalogId": "b7aa877f2b97f6f0"
    }
  },
  {
    "uid": "APT-ENG-0533",
    "questionHtml": "<p>Sentences of a paragraph are given below. While the first and the last sentences are in correct order, the sentences in between are jumbled up. Arrange the sentences in the right order to form a meaningful and coherent paragraph. <br>S1. Ram Mohan was a lover of his country. <br>P. David said that it would be a good plan to have an English school and college. <br>Q. He was talking with David about uplifting the mind of Indians. <br>R. So, he also thought that this subject was very interesting. <br>S. David also had a strong bond with India. <br>S6. Indians and Europeans met next year to put this idea into shape.</p>\n<ol style=\"list-style-type:upper-alpha\"><li>QSRP</li><li>SRPQ</li><li>RPQS</li><li>RSPQ</li></ol>",
    "options": [
      "QSRP",
      "SRPQ",
      "RPQS",
      "RSPQ"
    ],
    "answer": "A",
    "type": "MCQ",
    "subject": "English",
    "subtopic": "Para Jumble",
    "year": null,
    "_source": {
      "sourceKind": "bossxcode-web",
      "examBody": "BossXCode",
      "examName": "BossXCode",
      "pageUrl": "https://pt.bossxcode.unaux.com/play#paper-58db70b094c063e3",
      "sourceId": "e08eaa6965121840",
      "originalQNum": "20",
      "topic": "Para Jumble",
      "catalogId": "0353496bb1d7b0f0"
    }
  },
  {
    "uid": "APT-ENG-0534",
    "questionHtml": "<p>Sentences of a paragraph are given below in jumbled order. Arrange the sentences in the right order to form a meaningful and coherent paragraph. <br>A. At its height, around 1,200 years ago, the city of Calakmul had a population of about 50,000 people, but the kingdom as a whole numbered more than 1.5 million. <br>B. Deep in the jungle of southern Mexico lie the ruins of a city that thrived for centuries before it was abandoned more than 1,000 years ago. <br>C. Archaeologists have uncovered 6,750 structures here—the largest is this pyramid temple, called, simply, 'Structure 2.’<br>D. Calakmul was once one of the two duelling superpowers–along with Tikal—of the Classical Mayan civilisation.</p>\n<ol style=\"list-style-type:upper-alpha\"><li><p>DBCA</p></li><li><p>ACDB</p></li><li><p>BCDA</p></li><li><p>BDAC</p></li></ol>",
    "options": [
      "<p>DBCA</p>",
      "<p>ACDB</p>",
      "<p>BCDA</p>",
      "<p>BDAC</p>"
    ],
    "answer": "D",
    "type": "MCQ",
    "subject": "English",
    "subtopic": "Para Jumble",
    "year": null,
    "_source": {
      "sourceKind": "bossxcode-web",
      "examBody": "BossXCode",
      "examName": "BossXCode",
      "pageUrl": "https://pt.bossxcode.unaux.com/play#paper-bbf3f6915c76edfb",
      "sourceId": "386d7c1988c7edfd",
      "originalQNum": "21",
      "topic": "Para Jumble",
      "catalogId": "b7aa877f2b97f6f0"
    }
  },
  {
    "uid": "APT-ENG-0535",
    "questionHtml": "<p>Sentences of a paragraph are given below in jumbled order. Arrange the sentences in the right order to form a meaningful and coherent paragraph. <br>A. “I have already spent it,” the thief replied. <br>B. “What! I will take you to the police right now,” Arun thundered. <br>C. “Give me back my money,” Arun said to the thief. <br>D. “Sir, please have some mercy on me,” the thief pleaded.</p>\n<ol style=\"list-style-type:upper-alpha\"><li><p>CABD</p></li><li><p>ADBC</p></li><li><p>CBAD</p></li><li><p>BCAD</p></li></ol>",
    "options": [
      "<p>CABD</p>",
      "<p>ADBC</p>",
      "<p>CBAD</p>",
      "<p>BCAD</p>"
    ],
    "answer": "A",
    "type": "MCQ",
    "subject": "English",
    "subtopic": "Para Jumble",
    "year": null,
    "_source": {
      "sourceKind": "bossxcode-web",
      "examBody": "BossXCode",
      "examName": "BossXCode",
      "pageUrl": "https://pt.bossxcode.unaux.com/play#paper-bbf3f6915c76edfb",
      "sourceId": "4fcf20edf7817874",
      "originalQNum": "22",
      "topic": "Para Jumble",
      "catalogId": "b7aa877f2b97f6f0"
    }
  }
]
