[
  {
    "uid": "APT-QNT-12730",
    "questionHtml": "<p>Which of the following idioms means ‘to steal from a shop’?</p>\n<ol style=\"list-style-type:upper-alpha\"><li><p>Golden opportunity</p></li><li><p>Green thumb</p></li><li><p>Five-finger discount</p></li><li><p>Black sheep</p></li></ol>",
    "options": [
      "<p>Golden opportunity</p>",
      "<p>Green thumb</p>",
      "<p>Five-finger discount</p>",
      "<p>Black sheep</p>"
    ],
    "answer": "C",
    "type": "MCQ",
    "subject": "Quant",
    "subtopic": "Discount",
    "year": 2024,
    "_source": {
      "sourceKind": "aptitude-web",
      "sourceProvider": "AptitudeBank",
      "examBody": "SSC",
      "examName": "SSC CGL Tier 1",
      "year": 2024,
      "testSeries": "English [P.Y.P] SSC CGL 2024 (36 Sets) 09/09/2024 - 26/09/2024",
      "paperTitle": "SSC CGL 2024 English [09-09-2024 (Shift III)]",
      "product": "SSC Eduquity Test Pass : 2026 Exam: SSC",
      "tier": "SSC CGL Tier 1",
      "testType": "Sectional Tests",
      "pageUrl": "https://aptitude-bank.internal/play#paper-b4a0734cbdec09c7",
      "sourceId": "bb6e35e7ddfbfcc6",
      "originalQNum": "9",
      "topic": "Miscellaneous",
      "catalogId": "fb335190842000df"
    }
  }
]
