{
  "generatedAt": "2026-06-09T21:50:39.905Z",
  "shardKey": "2000-s0",
  "yearSetKey": "2000-s0",
  "year": 2000,
  "set": null,
  "label": "2000",
  "questionCount": 44,
  "recordsByQuestionUid": {
    "go:624": {
      "title": "GATE CSE 2000 | Question: 1.1",
      "year": "gatecse-2000",
      "link": "https://gateoverflow.in/624/gate-cse-2000-question-1-1",
      "question": "<p>The minimum number of cards to be dealt from an arbitrarily shuffled deck of $52$ cards to guarantee that three cards are from same suit is</p>\n<ol style=\"list-style-type:upper-alpha\">\n<li>$3$</li>\n<li>$8$</li>\n<li>$9$</li>\n<li>$12$</li>\n</ol>",
      "tags": [
        "gatecse-2000",
        "easy",
        "pigeonhole-principle",
        "combinatory"
      ],
      "question_uid": "go:624",
      "exam_uid": "cse:2000:set1:main:q1-1",
      "answer_uid": "v1:1.6.1",
      "answer_meta": {
        "type": "MCQ",
        "answer": "C",
        "tolerance": null,
        "source": "question_uid"
      }
    },
    "go:625": {
      "title": "GATE CSE 2000 | Question: 1.2",
      "year": "gatecse-2000",
      "link": "https://gateoverflow.in/625/gate-cse-2000-question-1-2",
      "question": "<p>An $n \\times n$ array $v$ is defined as follows:</p>\n<p>$v\\left[i,j\\right] = i - j$ for all $i, j, i \\leq n, 1 \\leq j \\leq n$</p>\n<p>The sum of the elements of the array $v$ is</p>\n<ol style=\"list-style-type:upper-alpha\">\n<li>$0$</li>\n<li>$n-1$</li>\n<li>$n^2 - 3n +2$</li>\n<li>$n^2 \\frac{\\left(n+1\\right)}{2}$</li>\n</ol>",
      "tags": [
        "gatecse-2000",
        "data-structures",
        "array",
        "easy"
      ],
      "question_uid": "go:625",
      "exam_uid": "cse:2000:set1:main:q1-2",
      "answer_uid": "v2:8.2.6",
      "answer_meta": {
        "type": "MCQ",
        "answer": "A",
        "tolerance": null,
        "source": "question_uid"
      }
    },
    "go:626": {
      "title": "GATE CSE 2000 | Question: 1.3",
      "year": "gatecse-2000",
      "link": "https://gateoverflow.in/626/gate-cse-2000-question-1-3",
      "question": "<p>The determinant of the matrix $$\\begin{bmatrix}2 &amp;0  &amp;0  &amp;0 \\\\  8&amp;  1&amp;  7&amp; 2\\\\  2&amp;  0&amp;2  &amp;0 \\\\  9&amp;0  &amp; 6 &amp; 1 \\end{bmatrix}$$</p>\n<ol style=\"list-style-type:upper-alpha\">\n<li>$4$</li>\n<li>$0$</li>\n<li>$15$</li>\n<li>$20$</li>\n</ol>",
      "tags": [
        "gatecse-2000",
        "linear-algebra",
        "easy",
        "determinant"
      ],
      "question_uid": "go:626",
      "exam_uid": "cse:2000:set1:main:q1-3",
      "answer_uid": "manual:go:626",
      "answer_meta": {
        "type": "MCQ",
        "answer": "A",
        "tolerance": null,
        "source": "question_uid"
      }
    },
    "go:627": {
      "title": "GATE CSE 2000 | Question: 1.4",
      "year": "gatecse-2000",
      "link": "https://gateoverflow.in/627/gate-cse-2000-question-1-4",
      "question": "<p>Let $S$ and $T$ be languages over $\\Sigma=\\{a,b\\}$ represented by the regular expressions $(a+b^*)^*$ and $(a+b)^*$, respectively. Which of the following is true?</p>\n<ol style=\"list-style-type:upper-alpha\">\n<li>$S \\subset T$</li>\n<li>$T \\subset S$</li>\n<li>$S = T$</li>\n<li>$S \\cap T = \\phi$</li>\n</ol>",
      "tags": [
        "gatecse-2000",
        "theory-of-computation",
        "regular-expression",
        "easy"
      ],
      "question_uid": "go:627",
      "exam_uid": "cse:2000:set1:main:q1-4",
      "answer_uid": "manual:go:627",
      "answer_meta": {
        "type": "MCQ",
        "answer": "C",
        "tolerance": null,
        "source": "question_uid"
      }
    },
    "go:628": {
      "title": "GATE CSE 2000 | Question: 1.5",
      "year": "gatecse-2000",
      "link": "https://gateoverflow.in/628/gate-cse-2000-question-1-5",
      "question": "<p>Let $L$ denote the languages generated by the grammar $S \\to 0S0 \\mid 00$.<br/>\nWhich of the following is TRUE?</p>\n<ol style=\"list-style-type:upper-alpha\">\n<li>$L = 0^+$</li>\n<li>$L$ is regular but not $0^+$</li>\n<li>$L$ is context free but not regular</li>\n<li>$L$ is not context free</li>\n</ol>",
      "tags": [
        "gatecse-2000",
        "theory-of-computation",
        "easy",
        "identify-class-language"
      ],
      "question_uid": "go:628",
      "exam_uid": "cse:2000:set1:main:q1-5",
      "answer_uid": "v2:10.9.6",
      "answer_meta": {
        "type": "MCQ",
        "answer": "B",
        "tolerance": null,
        "source": "question_uid"
      }
    },
    "go:629": {
      "title": "GATE CSE 2000 | Question: 1.6",
      "year": "gatecse-2000",
      "link": "https://gateoverflow.in/629/gate-cse-2000-question-1-6",
      "question": "<p>The number $43$ in $2's$ complement representation is</p>\n<ol style=\"list-style-type:upper-alpha\">\n<li>$01010101$</li>\n<li>$11010101$</li>\n<li>$00101011$</li>\n<li>$10101011$</li>\n</ol>",
      "tags": [
        "gatecse-2000",
        "digital-logic",
        "number-representation",
        "easy"
      ],
      "question_uid": "go:629",
      "exam_uid": "cse:2000:set1:main:q1-6",
      "answer_uid": "v2:6.24.15",
      "answer_meta": {
        "type": "MCQ",
        "answer": "C",
        "tolerance": null,
        "source": "question_uid"
      }
    },
    "go:631": {
      "title": "GATE CSE 2000 | Question: 1.8",
      "year": "gatecse-2000",
      "link": "https://gateoverflow.in/631/gate-cse-2000-question-1-8",
      "question": "<p>Comparing the time T1 taken for a single instruction on a pipelined CPU with time T2 taken on a non-pipelined but identical CPU, we can say that</p>\n<ol style=\"list-style-type: upper-alpha;\">\n<li>T1 ≤ T2</li>\n<li>T1 ≥ T2</li>\n<li>T1 &lt; T2</li>\n<li>T1 and T2 plus the time taken for one instruction fetch cycle</li>\n</ol>",
      "tags": [
        "gatecse-2000",
        "pipelining",
        "co-and-architecture",
        "easy"
      ],
      "question_uid": "go:631",
      "exam_uid": "cse:2000:set1:main:q1-8",
      "answer_uid": "manual:go:631",
      "answer_meta": {
        "type": "MCQ",
        "answer": "B",
        "tolerance": null,
        "source": "question_uid"
      }
    },
    "go:633": {
      "title": "GATE CSE 2000 | Question: 1.10",
      "year": "gatecse-2000",
      "link": "https://gateoverflow.in/633/gate-cse-2000-question-1-10",
      "question": "<p>The most appropriate matching for the following pairs$$\\begin{array}{ll} \\text{X: Indirect addressing} &amp; \\text{1: Loops } \\\\  \\text{Y: Immediate addressing } &amp; \\text{2: Pointers} \\\\   \\text{Z: Auto decrement addressing } &amp; \\text{3: Constants } \\\\  \\end{array}$$ is</p>\n<ol style=\"list-style-type:upper-alpha\">\n<li>$X - 3,  Y - 2,  Z - 1$</li>\n<li>$X - 1,  Y - 3,  Z - 2$</li>\n<li>$X - 2,  Y - 3,  Z - 1$</li>\n<li>$X - 3,  Y - 1,  Z - 2$</li>\n</ol>",
      "tags": [
        "gatecse-2000",
        "co-and-architecture",
        "normal",
        "addressing-modes"
      ],
      "question_uid": "go:633",
      "exam_uid": "cse:2000:set1:main:q1-10",
      "answer_uid": "v2:2.1.8",
      "answer_meta": {
        "type": "MCQ",
        "answer": "C",
        "tolerance": null,
        "source": "question_uid"
      }
    },
    "go:634": {
      "title": "GATE CSE 2000 | Question: 1.11",
      "year": "gatecse-2000",
      "link": "https://gateoverflow.in/634/gate-cse-2000-question-1-11",
      "question": "<p>The following C declarations:</p>\n<pre class=\"prettyprint lang-c_cpp\">struct node { \n    int i:\n    float j;\n };\n struct node *s[10];</pre>\n<p>define s to be:</p>\n<ol style=\"list-style-type:upper-alpha\">\n<li>An array, each element of which is a pointer to a structure of type node</li>\n<li>A structure of $2$ fields, each field being a pointer to an array of $10$ elements</li>\n<li>A structure of $3$ fields: an integer, a float, and an array of $10$ elements</li>\n<li>An array, each element of which is a structure of type node</li>\n</ol>",
      "tags": [
        "gatecse-2000",
        "programming",
        "programming-in-c",
        "easy",
        "structure"
      ],
      "question_uid": "go:634",
      "exam_uid": "cse:2000:set1:main:q1-11",
      "answer_uid": "v2:9.15.1",
      "answer_meta": {
        "type": "MCQ",
        "answer": "A",
        "tolerance": null,
        "source": "question_uid"
      }
    },
    "go:635": {
      "title": "GATE CSE 2000 | Question: 1.12",
      "year": "gatecse-2000",
      "link": "https://gateoverflow.in/635/gate-cse-2000-question-1-12",
      "question": "<p>The most appropriate matching for the following pairs$$\\begin{array}{|ll|ll|}\\hline X: &amp; \\text{m = malloc(5); m = NULL;} &amp; 1: &amp; \\text{using dangling pointers} \\\\\\hline  Y: &amp; \\text{free(n); n -&gt; value = 5;} &amp; 2: &amp; \\text{using uninitialized pointers} \\\\\\hline   Z: &amp; \\text{char *p , *p = ‘a’ ; } &amp; 3:  &amp; \\text{lost memory} \\\\\\hline \\end{array}$$ is:</p>\n<ol style=\"list-style-type:upper-alpha\">\n<li>$X - 1 \\ \\  Y - 3 \\ \\  Z - 2$</li>\n<li>$X - 2 \\ \\  Y - 1 \\ \\  Z - 3$</li>\n<li>$X - 3 \\ \\  Y - 2 \\ \\  Z - 1$</li>\n<li>$X - 3 \\ \\  Y - 1 \\ \\ Z - 2$</li>\n</ol>",
      "tags": [
        "gatecse-2000",
        "programming",
        "programming-in-c",
        "normal",
        "pointers"
      ],
      "question_uid": "go:635",
      "exam_uid": "cse:2000:set1:main:q1-12",
      "answer_uid": "v2:9.9.1",
      "answer_meta": {
        "type": "MCQ",
        "answer": "D",
        "tolerance": null,
        "source": "question_uid"
      }
    },
    "go:636": {
      "title": "GATE CSE 2000 | Question: 1.13",
      "year": "gatecse-2000",
      "link": "https://gateoverflow.in/636/gate-cse-2000-question-1-13",
      "question": "<p>The most appropriate matching for the following pairs</p>\n<p>$$\\begin{array}{|l|l|}\\hline \\text{X: depth first search}  &amp;  \\text{1: heap } \\\\\\hline  \\text{Y: breadth first search} &amp; \\text{2: queue} \\\\\\hline  \\text{Z: sorting} &amp; \\text{3: stack} \\\\\\hline \\end{array}$$</p>\n<p>is:</p>\n<ol style=\"list-style-type:upper-alpha\">\n<li>$\\text{X - 1,  Y - 2,  Z - 3}$</li>\n<li>$\\text{X - 3,  Y - 1,  Z - 2}$</li>\n<li>$\\text{X - 3,  Y - 2,  Z - 1}$</li>\n<li>$\\text{X - 2,  Y - 3,  Z - 1}$</li>\n</ol>",
      "tags": [
        "gatecse-2000",
        "algorithms",
        "easy",
        "graph-algorithms",
        "graph-search"
      ],
      "question_uid": "go:636",
      "exam_uid": "cse:2000:set1:main:q1-13",
      "answer_uid": "v2:1.14.2",
      "answer_meta": {
        "type": "MCQ",
        "answer": "C",
        "tolerance": null,
        "source": "question_uid"
      }
    },
    "go:637": {
      "title": "GATE CSE 2000 | Question: 1.14",
      "year": "gatecse-2000",
      "link": "https://gateoverflow.in/637/gate-cse-2000-question-1-14",
      "question": "<p>Consider the following nested representation of binary trees: $(X \\ Y \\ Z)$ indicates $Y$ and $Z$ are the left and right subtrees, respectively, of node $X$. Note that $Y$ and $Z$ may be $NULL$, or further nested. Which of the following represents a valid binary tree?</p>\n<ol style=\"list-style-type:upper-alpha\">\n<li>$(1 \\ 2 \\ (4 \\ 5 \\ 6 \\ 7))$</li>\n<li>$(1 \\ (2 \\ 3 \\ 4) \\ 5 \\ 6) \\ 7)$</li>\n<li>$(1 \\ (2 \\ 3  \\ 4) \\ (5 \\ 6  \\ 7))$</li>\n<li>$(1 \\ (2 \\ 3 \\ NULL) \\ (4 \\ 5))$</li>\n</ol>",
      "tags": [
        "gatecse-2000",
        "data-structures",
        "binary-tree",
        "easy"
      ],
      "question_uid": "go:637",
      "exam_uid": "cse:2000:set1:main:q1-14",
      "answer_uid": "v2:8.5.20",
      "answer_meta": {
        "type": "MCQ",
        "answer": "C",
        "tolerance": null,
        "source": "question_uid"
      }
    },
    "go:638": {
      "title": "GATE CSE 2000 | Question: 1.15",
      "year": "gatecse-2000",
      "link": "https://gateoverflow.in/638/gate-cse-2000-question-1-15",
      "question": "<p>Let $S$ be a sorted array of $n$ integers. Let $T(n)$ denote the time taken for the most efficient algorithm to determined if there are two elements with sum less than $1000$ in $S$. Which of the following statement is true?</p>\n<ol style=\"list-style-type:upper-alpha\">\n<li>$T (n)$ is $O(1)$</li>\n<li>$n \\leq  T(n) \\leq n \\log_2 n$</li>\n<li>$n \\log_2 n ≤ T(n) &lt; \\frac{n}{2}$</li>\n<li>$T(n) = \\left (\\frac{n}{2} \\right)$</li>\n</ol>",
      "tags": [
        "gatecse-2000",
        "easy",
        "algorithms",
        "time-complexity"
      ],
      "question_uid": "go:638",
      "exam_uid": "cse:2000:set1:main:q1-15",
      "answer_uid": "manual:go:638",
      "answer_meta": {
        "type": "MCQ",
        "answer": "A",
        "tolerance": null,
        "source": "question_uid"
      }
    },
    "go:639": {
      "title": "GATE CSE 2000 | Question: 1.16",
      "year": "gatecse-2000",
      "link": "https://gateoverflow.in/639/gate-cse-2000-question-1-16",
      "question": "<p>Aliasing in the context of programming languages refers to</p>\n<ol style=\"list-style-type:upper-alpha\">\n<li>multiple variables having the same memory location</li>\n<li>multiple variables having the same value</li>\n<li>multiple variables having the same identifier</li>\n<li>multiple uses of the same variable</li>\n</ol>",
      "tags": [
        "gatecse-2000",
        "programming",
        "easy",
        "aliasing"
      ],
      "question_uid": "go:639",
      "exam_uid": "cse:2000:set1:main:q1-16",
      "answer_uid": "v2:9.1.1",
      "answer_meta": {
        "type": "MCQ",
        "answer": "A",
        "tolerance": null,
        "source": "question_uid"
      }
    },
    "go:640": {
      "title": "GATE CSE 2000 | Question: 1.17, ISRO2015-79",
      "year": "gatecse-2000",
      "link": "https://gateoverflow.in/640/gate-cse-2000-question-1-17-isro2015-79",
      "question": "<p>Consider the following C declaration:</p>\n<pre class=\"prettyprint linenums lang-c_cpp\" data-pbcklang=\"c_cpp\" data-pbcktabsize=\"4\">struct {\n    short x[5];  \n    union { \n        float y; \n        long z; \n    } u;\n )t;</pre>\n<p>Assume that the objects of the type short, float and long occupy $2$ bytes, $4$ bytes and $8$ bytes, respectively. The memory requirement for variable $t$, ignoring alignment consideration, is:</p>\n<ol style=\"list-style-type:upper-alpha\">\n<li>$22$ bytes</li>\n<li>$14$ bytes</li>\n<li>$18$ bytes</li>\n<li>$10$ bytes</li>\n</ol>",
      "tags": [
        "gatecse-2000",
        "programming",
        "programming-in-c",
        "easy",
        "isro2015",
        "union"
      ],
      "question_uid": "go:640",
      "exam_uid": "cse:2000:set1:main:q1-17-isro2015-79",
      "answer_uid": "v2:9.18.1",
      "answer_meta": {
        "type": "MCQ",
        "answer": "C",
        "tolerance": null,
        "source": "question_uid"
      }
    },
    "go:641": {
      "title": "GATE CSE 2000 | Question: 1.18, ISRO2015-25",
      "year": "gatecse-2000",
      "link": "https://gateoverflow.in/641/gate-cse-2000-question-1-18-isro2015-25",
      "question": "<p>The number of tokens in the following C statement is</p>\n<pre class=\"prettyprint lang-c_cpp\">printf(\"i=%d, &amp;i=%x\", i, &amp;i);</pre>\n<ol style=\"list-style-type:upper-alpha\">\n<li>$3$</li>\n<li>$26$</li>\n<li>$10$</li>\n<li>$21$</li>\n</ol>",
      "tags": [
        "gatecse-2000",
        "compiler-design",
        "compiler-tokenization",
        "easy",
        "isro2015"
      ],
      "question_uid": "go:641",
      "exam_uid": "cse:2000:set1:main:q1-18-isro2015-25",
      "answer_uid": "v2:3.11.2",
      "answer_meta": {
        "type": "MCQ",
        "answer": "C",
        "tolerance": null,
        "source": "question_uid"
      }
    },
    "go:642": {
      "title": "GATE CSE 2000 | Question: 1.19, UGCNET-Dec2013-II: 30",
      "year": "gatecse-2000",
      "link": "https://gateoverflow.in/642/gate-cse-2000-question-1-19-ugcnet-dec2013-ii-30",
      "question": "<p>Which of the following derivations does a top-down parser use while parsing an input string? The input is scanned from left to right.</p>\n<ol style=\"list-style-type:upper-alpha\">\n<li>Leftmost derivation</li>\n<li>Leftmost derivation traced out in reverse</li>\n<li>Rightmost derivation </li>\n<li>Rightmost derivation traced out in reverse</li>\n</ol>",
      "tags": [
        "gatecse-2000",
        "compiler-design",
        "parsing",
        "normal",
        "ugcnetcse-dec2013-paper2"
      ],
      "question_uid": "go:642",
      "exam_uid": "cse:2000:set1:main:q1-19-ugcnet-dec2013-ii-30",
      "answer_uid": "v2:3.17.9",
      "answer_meta": {
        "type": "MCQ",
        "answer": "A",
        "tolerance": null,
        "source": "question_uid"
      }
    },
    "go:644": {
      "title": "GATE CSE 2000 | Question: 1.20, ISRO2008-47",
      "year": "gatecse-2000",
      "link": "https://gateoverflow.in/644/gate-cse-2000-question-1-20-isro2008-47",
      "question": "<p>Which of the following need not necessarily be saved on a context switch between processes?</p>\n<ol style=\"list-style-type:upper-alpha\">\n<li>General purpose registers</li>\n<li>Translation look-aside buffer</li>\n<li>Program counter</li>\n<li>All of the above</li>\n</ol>",
      "tags": [
        "gatecse-2000",
        "operating-system",
        "easy",
        "isro2008",
        "context-switch"
      ],
      "question_uid": "go:644",
      "exam_uid": "cse:2000:set1:main:q1-20-isro2008-47",
      "answer_uid": "v2:7.1.2",
      "answer_meta": {
        "type": "MCQ",
        "answer": "B",
        "tolerance": null,
        "source": "question_uid"
      }
    },
    "go:645": {
      "title": "GATE CSE 2000 | Question: 1.21",
      "year": "gatecse-2000",
      "link": "https://gateoverflow.in/645/gate-cse-2000-question-1-21",
      "question": "<p>Let $m[0]\\ldots m[4]$ be mutexes (binary semaphores) and $P[0]\\ldots P[4]$ be processes. <br/>\nSuppose each process $P[i]$ executes the following:</p>\n<pre class=\"prettyprint linenums lang-c_cpp\" data-pbcklang=\"c_cpp\" data-pbcktabsize=\"4\">     wait (m[i]); wait (m(i+1) mod 4]);\n     ........... \n     release (m[i]); release (m(i+1) mod 4]);</pre>\n<p>This could cause</p>\n<ol style=\"list-style-type:upper-alpha\">\n<li>Thrashing</li>\n<li>Deadlock</li>\n<li>Starvation, but not deadlock</li>\n<li>None of the above</li>\n</ol>",
      "tags": [
        "gatecse-2000",
        "operating-system",
        "process-synchronization",
        "normal"
      ],
      "question_uid": "go:645",
      "exam_uid": "cse:2000:set1:main:q1-21",
      "answer_uid": "v2:7.20.18",
      "answer_meta": {
        "type": "MCQ",
        "answer": "B",
        "tolerance": null,
        "source": "question_uid"
      }
    },
    "go:646": {
      "title": "GATE CSE 2000 | Question: 1.22, UGCNET-June2012-II: 11",
      "year": "gatecse-2000",
      "link": "https://gateoverflow.in/646/gate-cse-2000-question-1-22-ugcnet-june2012-ii-11",
      "question": "<p>B$^{+}$-trees are preferred to binary trees in databases because</p>\n<ol style=\"list-style-type:upper-alpha\"><li>Disk capacities are greater than memory capacities</li>\n<li>Disk access is much slower than memory access</li>\n<li>Disk data transfer rates are much less than memory data transfer rates</li>\n<li>Disks are more reliable than memory</li>\n</ol>",
      "tags": [
        "gatecse-2000",
        "databases",
        "b-tree",
        "normal",
        "ugcnetcse-june2012-paper2"
      ],
      "question_uid": "go:646",
      "exam_uid": "cse:2000:set1:main:q1-22-ugcnet-june2012-ii-11",
      "answer_uid": "v2:5.1.7",
      "answer_meta": {
        "type": "MCQ",
        "answer": "B",
        "tolerance": null,
        "source": "question_uid"
      }
    },
    "go:648": {
      "title": "GATE CSE 2000 | Question: 2.1",
      "year": "gatecse-2000",
      "link": "https://gateoverflow.in/648/gate-cse-2000-question-2-1",
      "question": "<p>X, Y and Z are closed intervals of unit length on the real line. The overlap of X and Y is half a unit. The overlap of Y and Z is also half a unit. Let the overlap of X and Z be k units. Which of the following is true?</p>\n<ol style=\"list-style-type:upper-alpha\">\n<li>k must be 1</li>\n<li>k must be 0</li>\n<li>k can take any value between 0 and 1</li>\n<li>None of the above</li>\n</ol>",
      "tags": [
        "gatecse-2000",
        "numerical-methods",
        "normal"
      ],
      "question_uid": "go:648",
      "exam_uid": "cse:2000:set1:main:q2-1",
      "answer_uid": "manual:go:648",
      "answer_meta": {
        "type": "MCQ",
        "answer": "C",
        "tolerance": null,
        "source": "question_uid"
      }
    },
    "go:649": {
      "title": "GATE CSE 2000 | Question: 2.2",
      "year": "gatecse-2000",
      "link": "https://gateoverflow.in/649/gate-cse-2000-question-2-2",
      "question": "<p>$E_{1}$ and $E_{2}$  are events in a probability space satisfying the following constraints:</p>\n<ul>\n<li>$Pr$$\\left ( E_{1} \\right )$ = $Pr$$\\left ( E_{2} \\right )$</li>\n<li>$Pr$$\\left ( E_{1}\\cup E_{2} \\right )$ = $1$</li>\n<li>$E_{1}$ and $E_{2}$ are independent</li>\n</ul>\n<p>The value of $Pr$$\\left ( E_{1} \\right )$, the probability of the event $E_{1}$,  is</p>\n<ol style=\"list-style-type:upper-alpha\">\n<li> $0$</li>\n<li>$\\dfrac{1}{4}$</li>\n<li>$\\dfrac{1}{2}$</li>\n<li> $1$</li>\n</ol>",
      "tags": [
        "gatecse-2000",
        "probability",
        "easy",
        "independent-events"
      ],
      "question_uid": "go:649",
      "exam_uid": "cse:2000:set1:main:q2-2",
      "answer_uid": "v1:7.9.3",
      "answer_meta": {
        "type": "MCQ",
        "answer": "D",
        "tolerance": null,
        "source": "question_uid"
      }
    },
    "go:650": {
      "title": "GATE CSE 2000 | Question: 2.3",
      "year": "gatecse-2000",
      "link": "https://gateoverflow.in/650/gate-cse-2000-question-2-3",
      "question": "<p>Let $S = \\sum_{i=3}^{100} i \\log_{2} i$, and $T = \\int_{2}^{100} x \\log_{2}x dx$.</p>\n<p>Which of the following statements is true?</p>\n<ol style=\"list-style-type:upper-alpha\">\n<li>$S &gt; T$</li>\n<li>$S = T$</li>\n<li>$S &lt; T$ and $2S &gt; T$</li>\n<li>$2S ≤ T$</li>\n</ol>",
      "tags": [
        "gatecse-2000",
        "calculus",
        "integration",
        "normal"
      ],
      "question_uid": "go:650",
      "exam_uid": "cse:2000:set1:main:q2-3",
      "answer_uid": "v1:5.4.3",
      "answer_meta": {
        "type": "MCQ",
        "answer": "A",
        "tolerance": null,
        "source": "question_uid"
      }
    },
    "go:651": {
      "title": "GATE CSE 2000 | Question: 2.4",
      "year": "gatecse-2000",
      "link": "https://gateoverflow.in/651/gate-cse-2000-question-2-4",
      "question": "<p>A polynomial $p(x)$ satisfies the following:</p>\n<ul>\n<li>$p(1) = p(3) = p(5) = 1$ </li>\n<li>$p(2) = p(4) = -1$</li>\n</ul>\n<p>The minimum degree of such a polynomial is</p>\n<ol style=\"list-style-type:upper-alpha\">\n<li>$1$</li>\n<li>$2$</li>\n<li>$3$</li>\n<li>$4$</li>\n</ol>",
      "tags": [
        "gatecse-2000",
        "set-theory&algebra",
        "normal",
        "polynomials"
      ],
      "question_uid": "go:651",
      "exam_uid": "cse:2000:set1:main:q2-4",
      "answer_uid": "manual:go:651",
      "answer_meta": {
        "type": "MCQ",
        "answer": "D",
        "tolerance": null,
        "source": "question_uid"
      }
    },
    "go:652": {
      "title": "GATE CSE 2000 | Question: 2.5",
      "year": "gatecse-2000",
      "link": "https://gateoverflow.in/652/gate-cse-2000-question-2-5",
      "question": "<p>A relation $R$ is defined on the set of integers as $xRy$ iff $(x + y)$ is even. Which of the following statements is true?</p>\n<ol style=\"list-style-type:upper-alpha\">\n<li>$R$ is not an equivalence relation</li>\n<li>$R$ is an equivalence relation having $1$ equivalence class</li>\n<li>$R$ is an equivalence relation having $2$ equivalence classes</li>\n<li>$R$ is an equivalence relation having $3$ equivalence classes</li>\n</ol>",
      "tags": [
        "gatecse-2000",
        "set-theory&algebra",
        "relations",
        "normal"
      ],
      "question_uid": "go:652",
      "exam_uid": "cse:2000:set1:main:q2-5",
      "answer_uid": "manual:go:652",
      "answer_meta": {
        "type": "MCQ",
        "answer": "C",
        "tolerance": null,
        "source": "question_uid"
      }
    },
    "go:653": {
      "title": "GATE CSE 2000 | Question: 2.6",
      "year": "gatecse-2000",
      "link": "https://gateoverflow.in/653/gate-cse-2000-question-2-6",
      "question": "<p>Let $P(S)$ denotes the power set of set $S.$ Which of the following is always true?</p>\n<ol start=\"1\" style=\"list-style-type: upper-alpha;\">\n<li>$P(P(S)) = P(S)$</li>\n<li>$P(S) ∩ P(P(S)) = \\{ Ø \\}$</li>\n<li>$P(S) ∩ S = P(S)$</li>\n<li>$S ∉ P(S)$</li>\n</ol>",
      "tags": [
        "gatecse-2000",
        "set-theory&algebra",
        "easy",
        "set-theory"
      ],
      "question_uid": "go:653",
      "exam_uid": "cse:2000:set1:main:q2-6",
      "answer_uid": "manual:go:653",
      "answer_meta": {
        "type": "MCQ",
        "answer": "B",
        "tolerance": null,
        "source": "question_uid"
      }
    },
    "go:654": {
      "title": "GATE CSE 2000 | Question: 2.7",
      "year": "gatecse-2000",
      "link": "https://gateoverflow.in/654/gate-cse-2000-question-2-7",
      "question": "<p>Let $a, b, c, d$ be propositions. Assume that the equivalence $a ⇔ ( b \\vee \\neg b)$ and $b ⇔c$ hold. Then the truth-value of the formula $(a ∧ b) → (a ∧ c) ∨ d$ is always</p>\n<ol style=\"list-style-type:upper-alpha\">\n<li>True</li>\n<li>False</li>\n<li>Same as the truth-value of $b$</li>\n<li>Same as the truth-value of $d$</li>\n</ol>",
      "tags": [
        "gatecse-2000",
        "mathematical-logic",
        "normal",
        "propositional-logic"
      ],
      "question_uid": "go:654",
      "exam_uid": "cse:2000:set1:main:q2-7",
      "answer_uid": "v1:3.3.17",
      "answer_meta": {
        "type": "MCQ",
        "answer": "A",
        "tolerance": null,
        "source": "question_uid"
      }
    },
    "go:656": {
      "title": "GATE CSE 2000 | Question: 2.9",
      "year": "gatecse-2000",
      "link": "https://gateoverflow.in/656/gate-cse-2000-question-2-9",
      "question": "<p>Consider the following decision problems:</p>\n<p>$(P1):$ Does a given finite state machine accept a given string?</p>\n<p>$(P2):$ Does a given context free grammar generate an infinite number of strings?</p>\n<p>Which of the following statements is true?</p>\n<ol style=\"list-style-type:upper-alpha\">\n<li>Both$(P1)$ and $(P2)$ are decidable</li>\n<li>Neither $(P1)$ nor $(P2)$ is decidable</li>\n<li>Only $(P1)$ is decidable</li>\n<li>Only $(P2)$ is decidable</li>\n</ol>",
      "tags": [
        "gatecse-2000",
        "theory-of-computation",
        "decidability",
        "normal"
      ],
      "question_uid": "go:656",
      "exam_uid": "cse:2000:set1:main:q2-9",
      "answer_uid": "v2:10.5.10",
      "answer_meta": {
        "type": "MCQ",
        "answer": "A",
        "tolerance": null,
        "source": "question_uid"
      }
    },
    "go:657": {
      "title": "GATE CSE 2000 | Question: 2.10",
      "year": "gatecse-2000",
      "link": "https://gateoverflow.in/657/gate-cse-2000-question-2-10",
      "question": "<p>The simultaneous equations on the Boolean variables $x, y, z$ and $w$,</p>\n<ul>\n<li>$x + y + z = 1 $</li>\n<li>$xy = 0$</li>\n<li>$xz + w = 1$</li>\n<li>$xy + \\bar{z}\\bar{w} = 0$</li>\n</ul>\n<p>have the following solution for $x, y, z$ and $w,$ respectively:</p>\n<ol style=\"list-style-type:upper-alpha\">\n<li>$0 \\ 1 \\ 0 \\ 0$</li>\n<li>$1 \\ 1 \\ 0 \\ 1$</li>\n<li>$1 \\ 0 \\ 1 \\ 1$</li>\n<li>$1 \\ 0 \\ 0 \\ 0$</li>\n</ol>",
      "tags": [
        "gatecse-2000",
        "digital-logic",
        "boolean-algebra",
        "easy"
      ],
      "question_uid": "go:657",
      "exam_uid": "cse:2000:set1:main:q2-10",
      "answer_uid": "v2:6.3.13",
      "answer_meta": {
        "type": "MCQ",
        "answer": "C",
        "tolerance": null,
        "source": "question_uid"
      }
    },
    "go:658": {
      "title": "GATE CSE 2000 | Question: 2.11",
      "year": "gatecse-2000",
      "link": "https://gateoverflow.in/658/gate-cse-2000-question-2-11",
      "question": "<p>Which functions does NOT implement the Karnaugh map given below?</p>\n<p>                                        </p>\n<p style=\"text-align:center\"><img alt=\"\" height=\"227\" src=\"/Gate_QA/question-images/2942936006174363835.webp\" width=\"229\"/></p>\n<ol style=\"list-style-type:upper-alpha\">\n<li>$(w + x) y$</li>\n<li>$xy + yw$</li>\n<li>$(w + x) (\\bar{w} + y) (\\bar{x} + y)$</li>\n<li>None of the above</li>\n</ol>",
      "tags": [
        "gatecse-2000",
        "digital-logic",
        "k-map",
        "normal"
      ],
      "question_uid": "go:658",
      "exam_uid": "cse:2000:set1:main:q2-11",
      "answer_uid": "v2:6.18.9",
      "answer_meta": {
        "type": "MCQ",
        "answer": "D",
        "tolerance": null,
        "source": "question_uid"
      }
    },
    "go:659": {
      "title": "GATE CSE 2000 | Question: 2.12",
      "year": "gatecse-2000",
      "link": "https://gateoverflow.in/659/gate-cse-2000-question-2-12",
      "question": "<p>The following arrangement of master-slave flip flops</p>\n<p style=\"text-align:center\"><img alt=\"\" height=\"245\" src=\"/Gate_QA/question-images/8492054730077204303.webp\" width=\"406\"/></p>\n<p>has the initial state of $P, Q$ as $0, 1$ (respectively). After three clock cycles the output state $P, Q$ is (respectively),</p>\n<ol style=\"list-style-type:upper-alpha\">\n<li>$1, 0$</li>\n<li>$1, 1$</li>\n<li>$0, 0$</li>\n<li>$0, 1$</li>\n</ol>",
      "tags": [
        "gatecse-2000",
        "digital-logic",
        "circuit-output",
        "normal",
        "flip-flop"
      ],
      "question_uid": "go:659",
      "exam_uid": "cse:2000:set1:main:q2-12",
      "answer_uid": "v2:6.7.17",
      "answer_meta": {
        "type": "MCQ",
        "answer": "A",
        "tolerance": null,
        "source": "question_uid"
      }
    },
    "go:661": {
      "title": "GATE CSE 2000 | Question: 2.14",
      "year": "gatecse-2000",
      "link": "https://gateoverflow.in/661/gate-cse-2000-question-2-14",
      "question": "<p>Consider the values of $A = 2.0 \\times 10^{30}, B = -2.0 \\times 10^{30}, C = 1.0,$ and the sequence </p>\n<pre class=\"prettyprint lang-c_cpp\">   X:= A + B          Y:= A + C   \n   X:= X + C          Y:= Y + B</pre>\n<p>executed on a computer where floating point numbers are represented with $32$ bits. The values for $X$ and $Y$ will be</p>\n<ol style=\"list-style-type:upper-alpha\">\n<li>$X = 1.0, Y = 1.0$</li>\n<li>$X = 1.0, Y = 0.0$</li>\n<li>$X = 0.0, Y = 1.0$</li>\n<li>$X = 0.0, Y = 0.0$</li>\n</ol>",
      "tags": [
        "gatecse-2000",
        "digital-logic",
        "number-representation",
        "normal"
      ],
      "question_uid": "go:661",
      "exam_uid": "cse:2000:set1:main:q2-14",
      "answer_uid": "v2:6.24.16",
      "answer_meta": {
        "type": "MCQ",
        "answer": "B",
        "tolerance": null,
        "source": "question_uid"
      }
    },
    "go:662": {
      "title": "GATE CSE 2000 | Question: 2.15",
      "year": "gatecse-2000",
      "link": "https://gateoverflow.in/662/gate-cse-2000-question-2-15",
      "question": "<p>Suppose you are given an array $s[1....n]$ and a procedure reverse $(s, i, j)$ which reverses the order of elements in $s$ between positions $i$ and $j$ (both inclusive). What does the following sequence do, where $1 \\leqslant k \\leqslant n$:</p>\n<pre class=\"prettyprint lang-c_cpp\">           reverse (s, 1, k);\n           reverse (s, k+1, n);\n           reverse (s, 1, n);</pre>\n<ol style=\"list-style-type:upper-alpha\">\n<li>Rotates $s$ left by $k$ positions</li>\n<li>Leaves $s$ unchanged </li>\n<li>Reverses all elements of $s$</li>\n<li>None of the above</li>\n</ol>",
      "tags": [
        "gatecse-2000",
        "algorithms",
        "normal",
        "identify-function"
      ],
      "question_uid": "go:662",
      "exam_uid": "cse:2000:set1:main:q2-15",
      "answer_uid": "v2:1.18.11",
      "answer_meta": {
        "type": "MCQ",
        "answer": "A",
        "tolerance": null,
        "source": "question_uid"
      }
    },
    "go:663": {
      "title": "GATE CSE 2000 | Question: 2.16",
      "year": "gatecse-2000",
      "link": "https://gateoverflow.in/663/gate-cse-2000-question-2-16",
      "question": "<p>Let LASTPOST, LASTIN and LASTPRE denote the last vertex visited `in a postorder, inorder and preorder traversal respectively, of a complete binary tree. Which of the following is always true?</p>\n<ol style=\"list-style-type:upper-alpha\">\n<li>LASTIN = LASTPOST</li>\n<li>LASTIN = LASTPRE</li>\n<li>LASTPRE = LASTPOST</li>\n<li>None of the above</li>\n</ol>",
      "tags": [
        "gatecse-2000",
        "data-structures",
        "binary-tree",
        "normal"
      ],
      "question_uid": "go:663",
      "exam_uid": "cse:2000:set1:main:q2-16",
      "answer_uid": "v2:8.5.21",
      "answer_meta": {
        "type": "MCQ",
        "answer": "D",
        "tolerance": null,
        "source": "question_uid"
      }
    },
    "go:664": {
      "title": "GATE CSE 2000 | Question: 2.17",
      "year": "gatecse-2000",
      "link": "https://gateoverflow.in/664/gate-cse-2000-question-2-17",
      "question": "<p>Consider the following functions</p>\n<ul>\n<li>$f(n) = 3n^{\\sqrt{n}}$</li>\n<li>$g(n) = 2^{\\sqrt{n}{\\log_{2}n}}$</li>\n<li>$h(n) = n!$</li>\n</ul>\n<p>Which of the following is true?</p>\n<ol style=\"list-style-type:upper-alpha\">\n<li>$h(n)$ is $O(f(n))$</li>\n<li>$h(n)$ is $O(g(n))$</li>\n<li>$g(n)$ is not $O(f(n))$</li>\n<li>$f(n)$ is $O(g(n))$</li>\n</ol>",
      "tags": [
        "gatecse-2000",
        "algorithms",
        "asymptotic-notations",
        "normal"
      ],
      "question_uid": "go:664",
      "exam_uid": "cse:2000:set1:main:q2-17",
      "answer_uid": "v2:1.4.3",
      "answer_meta": {
        "type": "MCQ",
        "answer": "D",
        "tolerance": null,
        "source": "question_uid"
      }
    },
    "go:665": {
      "title": "GATE CSE 2000 | Question: 2.18",
      "year": "gatecse-2000",
      "link": "https://gateoverflow.in/665/gate-cse-2000-question-2-18",
      "question": "<p>Let $G$ be an undirected connected graph with distinct edge weights. Let $e_{max}$ be the edge with maximum weight and $e_{min}$ the edge with minimum weight. Which of the following statements is false?</p>\n<ol style=\"list-style-type:upper-alpha\">\n<li>Every minimum spanning tree of $G$ must contain $e_{min}$</li>\n<li>If $e_{max}$ is in a minimum spanning tree, then its removal must disconnect $G$</li>\n<li>No minimum spanning tree contains $e_{max}$</li>\n<li>$G$ has a unique minimum spanning tree</li>\n</ol>",
      "tags": [
        "gatecse-2000",
        "algorithms",
        "spanning-tree",
        "normal"
      ],
      "question_uid": "go:665",
      "exam_uid": "cse:2000:set1:main:q2-18",
      "answer_uid": "manual:go:665",
      "answer_meta": {
        "type": "MCQ",
        "answer": "C",
        "tolerance": null,
        "source": "question_uid"
      }
    },
    "go:4208": {
      "title": "GATE CSE 2000 | Question: 2.19",
      "year": "gatecse-2000",
      "link": "https://gateoverflow.in/4208/gate-cse-2000-question-2-19",
      "question": "<p>Let $G$ be an undirected graph. Consider a depth-first traversal of $G$, and let $T$ be the resulting depth-first search tree. Let $u$ be a vertex in $G$ and let $v$ be the first new (unvisited) vertex visited after visiting $u$ in the traversal. Which of the following statement is always true?</p>\n<ol style=\"list-style-type:upper-alpha\">\n<li>$\\{u, v\\}$ must be an edge in $G$, and $u$ is a descendant of $v$ in $T$</li>\n<li>$\\{u, v\\}$ must be an edge in $G$, and $v$ is a descendant of $u$ in $T$</li>\n<li>If $\\{u, v\\}$ is not an edge in $G$ then $u$ is a leaf in $T$</li>\n<li>If $\\{u, v\\}$ is not an edge in $G$ then $u$ and $v$ must have the same parent in $T$</li>\n</ol>",
      "tags": [
        "gatecse-2000",
        "algorithms",
        "graph-algorithms",
        "normal"
      ],
      "question_uid": "go:4208",
      "exam_uid": "cse:2000:set1:main:q2-19",
      "answer_uid": "v2:1.14.3",
      "answer_meta": {
        "type": "MCQ",
        "answer": "C",
        "tolerance": null,
        "source": "question_uid"
      }
    },
    "go:667": {
      "title": "GATE CSE 2000 | Question: 2.20",
      "year": "gatecse-2000",
      "link": "https://gateoverflow.in/667/gate-cse-2000-question-2-20",
      "question": "<p>The value of $j$ at the end of the execution of the following C program:</p>\n<pre class=\"prettyprint lang-c_cpp\">int incr (int i)\n{ \n    static int count = 0;\n    count = count + i;\n    return (count);\n} \nmain  { \n    int i, j; \n    for (i = 0; i &lt;= 4; i++)\n       j = incr (i);\n} \n\n</pre>\n<p>is:</p>\n<ol style=\"list-style-type:upper-alpha\">\n<li>$10$</li>\n<li>$4$</li>\n<li>$6$</li>\n<li>$7$</li>\n</ol>",
      "tags": [
        "gatecse-2000",
        "programming",
        "programming-in-c",
        "easy"
      ],
      "question_uid": "go:667",
      "exam_uid": "cse:2000:set1:main:q2-20",
      "answer_uid": "v2:9.11.1",
      "answer_meta": {
        "type": "MCQ",
        "answer": "A",
        "tolerance": null,
        "source": "question_uid"
      }
    },
    "go:668": {
      "title": "GATE CSE 2000 | Question: 2.21, ISRO2015-24",
      "year": "gatecse-2000",
      "link": "https://gateoverflow.in/668/gate-cse-2000-question-2-21-isro2015-24",
      "question": "<p>Given the following expression grammar:</p>\n<p>$$\\begin{align}<br/>\nE &amp;\\to E * F \\mid F + E \\mid F \\\\[1em]<br/>\nF &amp;\\to F - F \\mid id<br/>\n\\end{align}$$</p>\n<p>Which of the following is true?</p>\n<ol style=\"list-style-type:upper-alpha\">\n<li>$*$ has higher precedence than $+$</li>\n<li>$-$ has higher precedence than $*$</li>\n<li>$+$ and $-$ have same precedence</li>\n<li>$+$ has higher precedence than $*$</li>\n</ol>",
      "tags": [
        "gatecse-2000",
        "operator-precedence",
        "normal",
        "compiler-design",
        "isro2015"
      ],
      "question_uid": "go:668",
      "exam_uid": "cse:2000:set1:main:q2-21-isro2015-24",
      "answer_uid": "v2:3.15.1",
      "answer_meta": {
        "type": "MCQ",
        "answer": "B",
        "tolerance": null,
        "source": "question_uid"
      }
    },
    "go:669": {
      "title": "GATE CSE 2000 | Question: 2.22",
      "year": "gatecse-2000",
      "link": "https://gateoverflow.in/669/gate-cse-2000-question-2-22",
      "question": "<p>Suppose the time to service a page fault is on the average $10$ milliseconds, while a memory access takes $1$ microsecond. Then a $99.99\\%$ hit ratio results in average memory access time of</p>\n<ol style=\"list-style-type:upper-alpha\">\n<li>$1.9999$ milliseconds</li>\n<li>$1$ millisecond</li>\n<li>$9.999$ microseconds</li>\n<li>$1.9999$ microseconds </li>\n</ol>",
      "tags": [
        "gatecse-2000",
        "operating-system",
        "easy",
        "virtual-memory"
      ],
      "question_uid": "go:669",
      "exam_uid": "cse:2000:set1:main:q2-22",
      "answer_uid": "manual:go:669",
      "answer_meta": {
        "type": "MCQ",
        "answer": "D",
        "tolerance": null,
        "source": "question_uid"
      }
    },
    "go:670": {
      "title": "GATE CSE 2000 | Question: 2.23",
      "year": "gatecse-2000",
      "link": "https://gateoverflow.in/670/gate-cse-2000-question-2-23",
      "question": "<p>Which of the following is not a valid deadlock prevention scheme?</p>\n<ol style=\"list-style-type:upper-alpha\">\n<li>Release all resources before requesting a new resource.</li>\n<li>Number the resources uniquely and never request a lower numbered resource than the last one requested.</li>\n<li>Never request a resource after releasing any resource.</li>\n<li>Request and all required resources be allocated before execution.</li>\n</ol>",
      "tags": [
        "gatecse-2000",
        "operating-system",
        "resource-allocation",
        "normal"
      ],
      "question_uid": "go:670",
      "exam_uid": "cse:2000:set1:main:q2-23",
      "answer_uid": "v2:7.21.10",
      "answer_meta": {
        "type": "MCQ",
        "answer": "C",
        "tolerance": null,
        "source": "question_uid"
      }
    },
    "go:671": {
      "title": "GATE CSE 2000 | Question: 2.24",
      "year": "gatecse-2000",
      "link": "https://gateoverflow.in/671/gate-cse-2000-question-2-24",
      "question": "<p>Given the following relation instance.</p>\n<p>$$\\begin{array}{|l|l|}\\hline \\text{X} &amp; \\text{Y} &amp; \\text{Z} \\\\\\hline   \\text{1} &amp; \\text{4} &amp; \\text{2} \\\\   \\text{1} &amp; \\text{5} &amp; \\text{3} \\\\  \\text{1} &amp; \\text{6} &amp; \\text{3} \\\\ \\text{3} &amp; \\text{2} &amp; \\text{2} \\\\\\hline \\end{array}$$</p>\n<p>Which of the following functional dependencies are satisfied by the instance?</p>\n<ol style=\"list-style-type:upper-alpha\">\n<li>$XY \\rightarrow Z$ and $Z \\rightarrow Y$</li>\n<li>$YZ \\rightarrow X$ and $Y \\rightarrow Z$</li>\n<li>$YZ \\rightarrow X$ and $X \\rightarrow Z$</li>\n<li>$XZ \\rightarrow Y$ and $Y \\rightarrow X$</li>\n</ol>",
      "tags": [
        "gatecse-2000",
        "databases",
        "database-normalization",
        "easy"
      ],
      "question_uid": "go:671",
      "exam_uid": "cse:2000:set1:main:q2-24",
      "answer_uid": "v2:5.5.15",
      "answer_meta": {
        "type": "MCQ",
        "answer": "B",
        "tolerance": null,
        "source": "question_uid"
      }
    },
    "go:672": {
      "title": "GATE CSE 2000 | Question: 2.25",
      "year": "gatecse-2000",
      "link": "https://gateoverflow.in/672/gate-cse-2000-question-2-25",
      "question": "<p>Given relations r(w, x) and s(y, z) the result of</p>\n<pre>select distinct w, x \nfrom r, s </pre>\n<p>is guaranteed to be same as r, provided.</p>\n<ol style=\"list-style-type:upper-alpha\">\n<li>r has no duplicates and s is non-empty</li>\n<li>r and s have no duplicates</li>\n<li>s has no duplicates and r is non-empty</li>\n<li>r and s have the same number of tuples</li>\n</ol>",
      "tags": [
        "gatecse-2000",
        "databases",
        "sql"
      ],
      "question_uid": "go:672",
      "exam_uid": "cse:2000:set1:main:q2-25",
      "answer_uid": "v2:5.18.10",
      "answer_meta": {
        "type": "MCQ",
        "answer": "A",
        "tolerance": null,
        "source": "question_uid"
      }
    },
    "go:688": {
      "title": "GATE CSE 2000 | Question: 17",
      "year": "gatecse-2000",
      "link": "https://gateoverflow.in/688/gate-cse-2000-question-17",
      "question": "<p>An array contains four occurrences of $0$, five occurrences of $1$, and three occurrences of $2$ in any order. The array is to be sorted using swap operations (elements that are swapped need to be adjacent).</p>\n<ol style=\"list-style-type:lower-alpha\">\n<li> What is the minimum number of swaps needed to sort such an array in the worst case?</li>\n<li> Give an ordering of  elements in the above array so that the minimum number of swaps needed to sort the array is maximum.</li>\n</ol>",
      "tags": [
        "gatecse-2000",
        "algorithms",
        "sorting",
        "normal",
        "descriptive"
      ],
      "question_uid": "go:688",
      "exam_uid": "cse:2000:set1:main:q17",
      "answer_uid": "v2:1.31.12",
      "answer_meta": {
        "type": "MCQ",
        "answer": "B",
        "tolerance": null,
        "source": "question_uid"
      }
    }
  }
}